Workbook
Name s_start: '02 Instellingen'!$C$6
Name s_periode: '02 Instellingen'!$C$7
Name s_dpm: '02 Instellingen'!$C$8
Name v_btw: '02 Instellingen'!$C$10
Name s_btwregime: '02 Instellingen'!$C$11
Name s_buffer: '02 Instellingen'!$C$12
Name s_finbuffer: '02 Instellingen'!$C$13
Name s_bank0: '02 Instellingen'!$C$14
Name s_omzet_jaar: '02 Instellingen'!$C$15
Name s_margin: '02 Instellingen'!$C$16
Name s_scenario: '02 Instellingen'!$C$17
Name p_omzetgroei: '02 Instellingen'!$H$21
Name p_marge_adj: '02 Instellingen'!$H$22
Name p_dso: '02 Instellingen'!$H$23
Name p_dpo: '02 Instellingen'!$H$24
Name p_dio: '02 Instellingen'!$H$25
Name p_kostengroei: '02 Instellingen'!$H$26
Name p_rente: '02 Instellingen'!$H$27
Name p_extra_capex: '02 Instellingen'!$H$28
Name s_capexmnd: '02 Instellingen'!$C$30
Name h_debiteuren: '03 Historie'!$C$21
Name h_voorraad: '03 Historie'!$C$22
Name h_crediteuren: '03 Historie'!$C$23
Name h_lening: '03 Historie'!$C$25
Name h_rc_limiet: '03 Historie'!$C$26
Name liq_end: '12 Liquiditeitsprognose'!$D$25:$AA$25
Name liq_tekort: '12 Liquiditeitsprognose'!$D$29:$AA$29
Name liq_net: '12 Liquiditeitsprognose'!$D$24:$AA$24
Name ctrl_status: '15 Controle'!$B$18

Sheet 01 Dashboard
B2: LIQUIDITEITSDASHBOARD - HANDELSBEDRIJF (FICTIEF)
B3: 01 Dashboard · Managementoverzicht · 24-maands liquiditeit · KPI's · signalen
B5: Huidige liquiditeit | E5: Liquiditeit +12 mnd | H5: Liquiditeit +24 mnd | K5: Minimale liquiditeit | N5: Max. financieringsbehoefte | Q5: Netto cashflow jaar 1 | T5: Min. buffer | W5: Omzet jaar 1
B6: =s_bank0 -> 300000 | E6: ='12 Liquiditeitsprognose'!P25 -> 316126.63 | H6: ='12 Liquiditeitsprognose'!AA25 -> 233935.61 | K6: =MIN(liq_end) -> 76529.965 | N6: =MAX(liq_tekort) -> 23470.035 | Q6: =SUM('12 Liquiditeitsprognose'!$D$24:$O$24) -> -105600.39 | T6: =s_buffer -> 100000 | W6: =SUM('05 Omzet & marge'!$D$8:$O$8) -> 5000000
B8: start maand 1 | E8: eind maand 12 | H8: eind maand 24 | K8: laagste punt | N8: t.o.v. buffer | Q8: 12 mnd | T8: gewenst | W8: excl. BTW
B10: Brutomarge | E10: DSO | H10: DPO | K10: DIO | N10: Cash Conversion Cycle | Q10: Pers.kosten / omzet | T10: Voorraad / omzet | W10: Actief scenario
B11: =s_margin+p_marge_adj -> 0.28 | E11: =p_dso -> 45 | H11: =p_dpo -> 40 | K11: =p_dio -> 55 | N11: =p_dio+p_dso-p_dpo -> 60 | Q11: =SUM('07 Personeel'!$D$13:$O$13)/SUM('05 Omzet & marge'!$D$8:$O$8) -> 0.13056 | T11: =('06 Werkkapitaal'!O10)/SUM('05 Omzet & marge'!$D$8:$O$8) -> 0.11723684 | W11: =s_scenario -> Base
B13: effectief | E13: debiteuren | H13: crediteuren | K13: voorraad | N13: DIO+DSO-DPO | Q13: jaar 1 | T13: jaar 1 | W13: gekozen
B15: BELANGRIJKSTE SIGNALEN (dynamisch)
B16: ="• Laagste liquiditeit: "&TEXT(MIN(liq_end),"€ #,##0")&" in "&TEXT(INDEX('12 Liquiditeitsprognose'!$D$5:$AA$5,MATCH(MIN(liq_end),liq_end,0)),"mmm-yyyy")&"." -> • Laagste liquiditeit: € 76,530 in Jan-2026.
B17: =IF(MIN(liq_end)<s_buffer,"• Dit ligt "&TEXT(s_buffer-MIN(liq_end),"€ #,##0")&" ONDER de gewenste buffer van "&TEXT(s_buffer,"€ #,##0")&".","• De liquiditeit blijft in alle maanden boven de gewenste buffer.") -> • Dit ligt € 23,470 ONDER de gewenste buffer van € 100,000.
B18: ="• Maximale financieringsbehoefte: "&TEXT(MAX(liq_tekort),"€ #,##0")&"." -> • Maximale financieringsbehoefte: € 23,470.
B19: ="• Cash Conversion Cycle: "&TEXT(p_dio+p_dso-p_dpo,"0")&" dagen (DIO "&TEXT(p_dio,"0")&" + DSO "&TEXT(p_dso,"0")&" - DPO "&TEXT(p_dpo,"0")&")." -> • Cash Conversion Cycle: 60 dagen (DIO 55 + DSO 45 - DPO 40).
B20: ="• Aantal maanden onder buffer: "&TEXT(COUNTIF(liq_end,"<"&s_buffer),"0")&" van 24." -> • Aantal maanden onder buffer: 1 van 24.
B21: =IF(MAX(liq_tekort)>0,"• Advies: onderzoek voorraadafbouw, snellere debiteureninning en/of extra financiering om het tekort te dichten.","• Advies: liquiditeit is toereikend; monitor werkkapitaal en seizoenspieken.") -> • Advies: onderzoek voorraadafbouw, snellere debiteureninning en/of extra financiering om het tekort te dichten.
B23: =ctrl_status -> ✅ MODEL OK - alle controles geslaagd

Sheet 02 Instellingen
B2: INSTELLINGEN & PARAMETERS
B3: 02 Instellingen · Centrale aannames · scenariomatrix · geldt voor het hele model
B5: ALGEMENE INSTELLINGEN (geel = invoer)
B6: Startdatum prognose | C6: 46023
B7: Prognoseperiode | C7: 24
B8: Dagen per maand (365/12) | C8: 30.4
B9: Valuta | C9: EUR
B10: BTW-tarief (hoog) | C10: 0.21
B11: BTW-aangifte | C11: Kwartaal
B12: Min. liquiditeitsbuffer | C12: 100000
B13: Gewenste financieringsbuffer | C13: 150000
B14: Openingssaldo bank (maand 1) | C14: 300000
B15: Basis jaaromzet | C15: 5000000
B16: Basis brutomarge | C16: 0.28
B17: Actief scenario | C17: Base
B19: SCENARIOMATRIX (kolom Actief wordt automatisch gekozen o.b.v. 'Actief scenario')
B20: Parameter | C20: Eenheid | D20: Base | E20: Best | F20: Worst | G20: Custom | H20: Actief
B21: Omzetgroei (Δ t.o.v. basis) | C21: % | D21: 0 | E21: 0.1 | F21: -0.1 | G21: 0 | H21: =INDEX($D$21:$G$21,MATCH(s_scenario,$D$20:$G$20,0)) -> 0
B22: Marge-aanpassing | C22: % | D22: 0 | E22: 0.02 | F22: -0.03 | G22: 0 | H22: =INDEX($D$22:$G$22,MATCH(s_scenario,$D$20:$G$20,0)) -> 0
B23: DSO - debiteurentermijn | C23: dagen | D23: 45 | E23: 38 | F23: 60 | G23: 45 | H23: =INDEX($D$23:$G$23,MATCH(s_scenario,$D$20:$G$20,0)) -> 45
B24: DPO - crediteurentermijn | C24: dagen | D24: 40 | E24: 45 | F24: 30 | G24: 40 | H24: =INDEX($D$24:$G$24,MATCH(s_scenario,$D$20:$G$20,0)) -> 40
B25: DIO - voorraaddagen | C25: dagen | D25: 55 | E25: 45 | F25: 75 | G25: 55 | H25: =INDEX($D$25:$G$25,MATCH(s_scenario,$D$20:$G$20,0)) -> 55
B26: Kostengroei (overige+pers.) | C26: % | D26: 0 | E26: -0.02 | F26: 0.05 | G26: 0 | H26: =INDEX($D$26:$G$26,MATCH(s_scenario,$D$20:$G$20,0)) -> 0
B27: Rente financiering | C27: % | D27: 0.06 | E27: 0.05 | F27: 0.08 | G27: 0.06 | H27: =INDEX($D$27:$G$27,MATCH(s_scenario,$D$20:$G$20,0)) -> 0.06
B28: Extra investering (eenmalig) | C28: € | D28: 0 | E28: 0 | F28: 200000 | G28: 0 | H28: =INDEX($D$28:$G$28,MATCH(s_scenario,$D$20:$G$20,0)) -> 0
B30: Maand extra investering (1-24) | C30: 12

Sheet 03 Historie
B2: HISTORISCHE CIJFERS
B3: 03 Historie · Vorig boekjaar, huidig boekjaar YTD · basis voor trends, seizoen en startposities
B5: WINST- & VERLIESREKENING (jaarbasis, fictief)
B6: Post | C6: Vorig jaar | D6: Huidig jaar (verw.) | E6: Bron
B7: Omzet | C7: 4650000 | D7: 5000000 | E7: Jaarrekening
B8: Inkoopwaarde omzet | C8: 3348000 | D8: 3600000 | E8: Jaarrekening
B9: Brutomarge | C9: =C7-C8 -> 1302000 | D9: =D7-D8 -> 1400000 | E9: Berekend
B10: Personeelskosten | C10: 700000 | D10: 750000 | E10: Jaarrekening
B11: Huisvesting | C11: 120000 | D11: 125000 | E11: Jaarrekening
B12: Overige bedrijfskosten | C12: 430000 | D12: 455000 | E12: Jaarrekening
B13: Afschrijvingen | C13: 95000 | D13: 100000 | E13: Jaarrekening
B14: Rente | C14: 55000 | D14: 60000 | E14: Jaarrekening
B15: Resultaat voor belasting | C15: =C9-C10-C11-C12-C13-C14 -> -98000 | D15: =D9-D10-D11-D12-D13-D14 -> -90000 | E15: Berekend
B16: Brutomarge % | C16: =IFERROR(C9/C7,0) -> 0.28 | D16: =IFERROR(D9/D7,0) -> 0.28
B18: BALANS - STARTPOSITIES (fictief, per begin prognose)
B19: Post | C19: Bedrag | D19: Toelichting
B20: Liquide middelen | C20: 300000 | D20: Start bank (zie Instellingen C14)
B21: Debiteuren | C21: 600000 | D21: Openingsstand debiteuren
B22: Voorraad | C22: 750000 | D22: Openingsstand voorraad (kostprijs)
B23: Crediteuren | C23: 500000 | D23: Openingsstand crediteuren
B24: Belastingschulden | C24: 120000 | D24: BTW/loonheffing openstaand
B25: Banklening | C25: 900000 | D25: Langlopende lening
B26: Rekening-courant krediet (limiet) | C26: 500000 | D26: RC-faciliteit bij bank
B27: Eigen vermogen | C27: 1200000 | D27: Balanspost

Sheet 04 Input prognose
B2: INPUT PROGNOSE - AANNAMES 24 MAANDEN
B3: 04 Input prognose · Seizoenspatroon omzet · overige ontvangsten/uitgaven · privé/dividend
B5: Maand | C5: Eenheid | D5: =EDATE(s_start,0) -> 46023 | E5: =EDATE(s_start,1) -> 46054 | F5: =EDATE(s_start,2) -> 46082 | G5: =EDATE(s_start,3) -> 46113 | H5: =EDATE(s_start,4) -> 46143 | I5: =EDATE(s_start,5) -> 46174 | J5: =EDATE(s_start,6) -> 46204 | K5: =EDATE(s_start,7) -> 46235 | L5: =EDATE(s_start,8) -> 46266 | M5: =EDATE(s_start,9) -> 46296 | N5: =EDATE(s_start,10) -> 46327 | O5: =EDATE(s_start,11) -> 46357 | P5: =EDATE(s_start,12) -> 46388 | Q5: =EDATE(s_start,13) -> 46419 | R5: =EDATE(s_start,14) -> 46447 | S5: =EDATE(s_start,15) -> 46478 | T5: =EDATE(s_start,16) -> 46508 | U5: =EDATE(s_start,17) -> 46539 | V5: =EDATE(s_start,18) -> 46569 | W5: =EDATE(s_start,19) -> 46600 | X5: =EDATE(s_start,20) -> 46631 | Y5: =EDATE(s_start,21) -> 46661 | Z5: =EDATE(s_start,22) -> 46692 | AA5: =EDATE(s_start,23) -> 46722
B6: Maandindex | D6: 1 | E6: 2 | F6: 3 | G6: 4 | H6: 5 | I6: 6 | J6: 7 | K6: 8 | L6: 9 | M6: 10 | N6: 11 | O6: 12 | P6: 13 | Q6: 14 | R6: 15 | S6: 16 | T6: 17 | U6: 18 | V6: 19 | W6: 20 | X6: 21 | Y6: 22 | Z6: 23 | AA6: 24
B8: Seizoensgewicht omzet (som 12 mnd = 100%) | C8: % | D8: 0.07 | E8: 0.07 | F8: 0.085 | G8: 0.085 | H8: 0.09 | I8: 0.085 | J8: 0.07 | K8: 0.06 | L8: 0.09 | M8: 0.1 | N8: 0.105 | O8: 0.09 | P8: 0.07 | Q8: 0.07 | R8: 0.085 | S8: 0.085 | T8: 0.09 | U8: 0.085 | V8: 0.07 | W8: 0.06 | X8: 0.09 | Y8: 0.1 | Z8: 0.105 | AA8: 0.09
B9: Overige ontvangsten (subsidie/rente/overig) | C9: € | D9: 0 | E9: 0 | F9: 0 | G9: 0 | H9: 0 | I9: 0 | J9: 0 | K9: 0 | L9: 0 | M9: 0 | N9: 0 | O9: 0 | P9: 0 | Q9: 0 | R9: 0 | S9: 0 | T9: 0 | U9: 0 | V9: 0 | W9: 0 | X9: 0 | Y9: 0 | Z9: 0 | AA9: 0
B10: Overige uitgaven (incidenteel) | C10: € | D10: 0 | E10: 0 | F10: 0 | G10: 0 | H10: 0 | I10: 0 | J10: 0 | K10: 0 | L10: 0 | M10: 0 | N10: 0 | O10: 0 | P10: 0 | Q10: 0 | R10: 0 | S10: 0 | T10: 0 | U10: 0 | V10: 0 | W10: 0 | X10: 0 | Y10: 0 | Z10: 0 | AA10: 0
B11: Privé-opnamen / dividend / management fee | C11: € | D11: 4000 | E11: 4000 | F11: 4000 | G11: 4000 | H11: 4000 | I11: 40000 | J11: 4000 | K11: 4000 | L11: 4000 | M11: 4000 | N11: 4000 | O11: 4000 | P11: 4000 | Q11: 4000 | R11: 4000 | S11: 4000 | T11: 4000 | U11: 40000 | V11: 4000 | W11: 4000 | X11: 4000 | Y11: 4000 | Z11: 4000 | AA11: 4000
B13: Controle: som seizoensgewicht mnd 1-12 | D13: =SUM(D8:O8) -> 1
B14: Controle: som seizoensgewicht mnd 13-24 | D14: =SUM(P8:AA8) -> 1

Sheet 05 Omzet & marge
B2: OMZET, INKOOPWAARDE & BRUTOMARGE
B3: 05 Omzet & marge · Omzet = jaaromzet × seizoensgewicht × (1 + scenario-omzetgroei)
B5: Maand | C5: Eenheid | D5: =EDATE(s_start,0) -> 46023 | E5: =EDATE(s_start,1) -> 46054 | F5: =EDATE(s_start,2) -> 46082 | G5: =EDATE(s_start,3) -> 46113 | H5: =EDATE(s_start,4) -> 46143 | I5: =EDATE(s_start,5) -> 46174 | J5: =EDATE(s_start,6) -> 46204 | K5: =EDATE(s_start,7) -> 46235 | L5: =EDATE(s_start,8) -> 46266 | M5: =EDATE(s_start,9) -> 46296 | N5: =EDATE(s_start,10) -> 46327 | O5: =EDATE(s_start,11) -> 46357 | P5: =EDATE(s_start,12) -> 46388 | Q5: =EDATE(s_start,13) -> 46419 | R5: =EDATE(s_start,14) -> 46447 | S5: =EDATE(s_start,15) -> 46478 | T5: =EDATE(s_start,16) -> 46508 | U5: =EDATE(s_start,17) -> 46539 | V5: =EDATE(s_start,18) -> 46569 | W5: =EDATE(s_start,19) -> 46600 | X5: =EDATE(s_start,20) -> 46631 | Y5: =EDATE(s_start,21) -> 46661 | Z5: =EDATE(s_start,22) -> 46692 | AA5: =EDATE(s_start,23) -> 46722
B6: Maandindex | D6: 1 | E6: 2 | F6: 3 | G6: 4 | H6: 5 | I6: 6 | J6: 7 | K6: 8 | L6: 9 | M6: 10 | N6: 11 | O6: 12 | P6: 13 | Q6: 14 | R6: 15 | S6: 16 | T6: 17 | U6: 18 | V6: 19 | W6: 20 | X6: 21 | Y6: 22 | Z6: 23 | AA6: 24
B8: Omzet (excl. BTW) | C8: € | D8: ='04 Input prognose'!D$8*s_omzet_jaar*(1+p_omzetgroei) -> 350000 | E8: ='04 Input prognose'!E$8*s_omzet_jaar*(1+p_omzetgroei) -> 350000 | F8: ='04 Input prognose'!F$8*s_omzet_jaar*(1+p_omzetgroei) -> 425000 | G8: ='04 Input prognose'!G$8*s_omzet_jaar*(1+p_omzetgroei) -> 425000 | H8: ='04 Input prognose'!H$8*s_omzet_jaar*(1+p_omzetgroei) -> 450000 | I8: ='04 Input prognose'!I$8*s_omzet_jaar*(1+p_omzetgroei) -> 425000 | J8: ='04 Input prognose'!J$8*s_omzet_jaar*(1+p_omzetgroei) -> 350000 | K8: ='04 Input prognose'!K$8*s_omzet_jaar*(1+p_omzetgroei) -> 300000 | ... AA8: ='04 Input prognose'!AA$8*s_omzet_jaar*(1+p_omzetgroei) -> 450000
B9: Effectieve brutomarge % | C9: % | D9: =s_margin+p_marge_adj -> 0.28 | E9: =s_margin+p_marge_adj -> 0.28 | F9: =s_margin+p_marge_adj -> 0.28 | G9: =s_margin+p_marge_adj -> 0.28 | H9: =s_margin+p_marge_adj -> 0.28 | I9: =s_margin+p_marge_adj -> 0.28 | J9: =s_margin+p_marge_adj -> 0.28 | K9: =s_margin+p_marge_adj -> 0.28 | ... AA9: =s_margin+p_marge_adj -> 0.28
B10: Brutowinst | C10: € | D10: =D8*D9 -> 98000 | E10: =E8*E9 -> 98000 | F10: =F8*F9 -> 119000 | G10: =G8*G9 -> 119000 | H10: =H8*H9 -> 126000 | I10: =I8*I9 -> 119000 | J10: =J8*J9 -> 98000 | K10: =K8*K9 -> 84000 | ... AA10: =AA8*AA9 -> 126000
B11: Inkoopwaarde omzet (COGS) | C11: € | D11: =D8-D10 -> 252000 | E11: =E8-E10 -> 252000 | F11: =F8-F10 -> 306000 | G11: =G8-G10 -> 306000 | H11: =H8-H10 -> 324000 | I11: =I8-I10 -> 306000 | J11: =J8-J10 -> 252000 | K11: =K8-K10 -> 216000 | ... AA11: =AA8-AA10 -> 324000
B12: Omzet incl. BTW (facturatie) | C12: € | D12: =D8*(1+v_btw) -> 423500 | E12: =E8*(1+v_btw) -> 423500 | F12: =F8*(1+v_btw) -> 514250 | G12: =G8*(1+v_btw) -> 514250 | H12: =H8*(1+v_btw) -> 544500 | I12: =I8*(1+v_btw) -> 514250 | J12: =J8*(1+v_btw) -> 423500 | K12: =K8*(1+v_btw) -> 363000 | ... AA12: =AA8*(1+v_btw) -> 544500
B14: Totaal omzet jaar 1 / jaar 2 | D14: =SUM(D8:O8) -> 5000000 | E14: =SUM(P8:AA8) -> 5000000

Sheet 06 Werkkapitaal
B2: WERKKAPITAAL - DEBITEUREN, VOORRAAD, CREDITEUREN
B3: 06 Werkkapitaal · Methodiek: streefsaldi o.b.v. DSO/DPO/DIO (days-based). Zie 16 Toelichting.
B5: Maand | C5: Eenheid | D5: =EDATE(s_start,0) -> 46023 | E5: =EDATE(s_start,1) -> 46054 | F5: =EDATE(s_start,2) -> 46082 | G5: =EDATE(s_start,3) -> 46113 | H5: =EDATE(s_start,4) -> 46143 | I5: =EDATE(s_start,5) -> 46174 | J5: =EDATE(s_start,6) -> 46204 | K5: =EDATE(s_start,7) -> 46235 | L5: =EDATE(s_start,8) -> 46266 | M5: =EDATE(s_start,9) -> 46296 | N5: =EDATE(s_start,10) -> 46327 | O5: =EDATE(s_start,11) -> 46357 | P5: =EDATE(s_start,12) -> 46388 | Q5: =EDATE(s_start,13) -> 46419 | R5: =EDATE(s_start,14) -> 46447 | S5: =EDATE(s_start,15) -> 46478 | T5: =EDATE(s_start,16) -> 46508 | U5: =EDATE(s_start,17) -> 46539 | V5: =EDATE(s_start,18) -> 46569 | W5: =EDATE(s_start,19) -> 46600 | X5: =EDATE(s_start,20) -> 46631 | Y5: =EDATE(s_start,21) -> 46661 | Z5: =EDATE(s_start,22) -> 46692 | AA5: =EDATE(s_start,23) -> 46722
B6: Maandindex | D6: 1 | E6: 2 | F6: 3 | G6: 4 | H6: 5 | I6: 6 | J6: 7 | K6: 8 | L6: 9 | M6: 10 | N6: 11 | O6: 12 | P6: 13 | Q6: 14 | R6: 15 | S6: 16 | T6: 17 | U6: 18 | V6: 19 | W6: 20 | X6: 21 | Y6: 22 | Z6: 23 | AA6: 24
B7: OPENINGSSTANDEN (begin maand 1) | C7: Deb/Vrd/Cred | D7: =h_debiteuren -> 600000 | E7: =h_voorraad -> 750000 | F7: =h_crediteuren -> 500000
B9: Inkoopwaarde omzet (COGS) | C9: € | D9: ='05 Omzet & marge'!D11 -> 252000 | E9: ='05 Omzet & marge'!E11 -> 252000 | F9: ='05 Omzet & marge'!F11 -> 306000 | G9: ='05 Omzet & marge'!G11 -> 306000 | H9: ='05 Omzet & marge'!H11 -> 324000 | I9: ='05 Omzet & marge'!I11 -> 306000 | J9: ='05 Omzet & marge'!J11 -> 252000 | K9: ='05 Omzet & marge'!K11 -> 216000 | ... AA9: ='05 Omzet & marge'!AA11 -> 324000
B10: Voorraad - streefsaldo (DIO) | C10: € | D10: =p_dio/s_dpm*D9 -> 455921.05 | E10: =p_dio/s_dpm*E9 -> 455921.05 | F10: =p_dio/s_dpm*F9 -> 553618.42 | G10: =p_dio/s_dpm*G9 -> 553618.42 | H10: =p_dio/s_dpm*H9 -> 586184.21 | I10: =p_dio/s_dpm*I9 -> 553618.42 | J10: =p_dio/s_dpm*J9 -> 455921.05 | K10: =p_dio/s_dpm*K9 -> 390789.47 | ... AA10: =p_dio/s_dpm*AA9 -> 586184.21
B11: Inkopen (excl. BTW) = COGS + Δvoorraad | C11: € | D11: =D9+D10-$E$7 -> -42078.947 | E11: =E9+E10-D10 -> 252000 | F11: =F9+F10-E10 -> 403697.37 | G11: =G9+G10-F10 -> 306000 | H11: =H9+H10-G10 -> 356565.79 | I11: =I9+I10-H10 -> 273434.21 | J11: =J9+J10-I10 -> 154302.63 | K11: =K9+K10-J10 -> 150868.42 | L11: =L9+L10-K10 -> 519394.74 | ... AA11: =AA9+AA10-Z10 -> 226302.63
B12: Inkopen incl. BTW | C12: € | D12: =D11*(1+v_btw) -> -50915.526 | E12: =E11*(1+v_btw) -> 304920 | F12: =F11*(1+v_btw) -> 488473.82 | G12: =G11*(1+v_btw) -> 370260 | H12: =H11*(1+v_btw) -> 431444.61 | I12: =I11*(1+v_btw) -> 330855.39 | J12: =J11*(1+v_btw) -> 186706.18 | K12: =K11*(1+v_btw) -> 182550.79 | ... AA12: =AA11*(1+v_btw) -> 273826.18
B13: Omzet incl. BTW (link) | C13: € | D13: ='05 Omzet & marge'!D12 -> 423500 | E13: ='05 Omzet & marge'!E12 -> 423500 | F13: ='05 Omzet & marge'!F12 -> 514250 | G13: ='05 Omzet & marge'!G12 -> 514250 | H13: ='05 Omzet & marge'!H12 -> 544500 | I13: ='05 Omzet & marge'!I12 -> 514250 | J13: ='05 Omzet & marge'!J12 -> 423500 | K13: ='05 Omzet & marge'!K12 -> 363000 | ... AA13: ='05 Omzet & marge'!AA12 -> 544500
B14: Debiteuren - streefsaldo (DSO) | C14: € | D14: =p_dso/s_dpm*D13 -> 626891.45 | E14: =p_dso/s_dpm*E13 -> 626891.45 | F14: =p_dso/s_dpm*F13 -> 761225.33 | G14: =p_dso/s_dpm*G13 -> 761225.33 | H14: =p_dso/s_dpm*H13 -> 806003.29 | I14: =p_dso/s_dpm*I13 -> 761225.33 | J14: =p_dso/s_dpm*J13 -> 626891.45 | K14: =p_dso/s_dpm*K13 -> 537335.53 | ... AA14: =p_dso/s_dpm*AA13 -> 806003.29
B15: Crediteuren - streefsaldo (DPO) | C15: € | D15: =p_dpo/s_dpm*D12 -> -66994.114 | E15: =p_dpo/s_dpm*E12 -> 401210.53 | F15: =p_dpo/s_dpm*F12 -> 642728.7 | G15: =p_dpo/s_dpm*G12 -> 487184.21 | H15: =p_dpo/s_dpm*H12 -> 567690.27 | I15: =p_dpo/s_dpm*I12 -> 435336.05 | J15: =p_dpo/s_dpm*J12 -> 245666.03 | K15: =p_dpo/s_dpm*K12 -> 240198.41 | ... AA15: =p_dpo/s_dpm*AA12 -> 360297.61
B16: Ontvangsten van klanten (kas-in) | C16: € | D16: =$D$7+D13-D14 -> 396608.55 | E16: =D14+E13-E14 -> 423500 | F16: =E14+F13-F14 -> 379916.12 | G16: =F14+G13-G14 -> 514250 | H16: =G14+H13-H14 -> 499722.04 | I16: =H14+I13-I14 -> 559027.96 | J16: =I14+J13-J14 -> 557833.88 | K16: =J14+K13-K14 -> 452555.92 | L16: =K14+L13-L14 -> 275832.24 | ... AA16: =Z14+AA13-AA14 -> 678833.88
B17: Betalingen aan leveranciers (kas-uit) | C17: € | D17: =$F$7+D12-D15 -> 516078.59 | E17: =D15+E12-E15 -> -163284.64 | F17: =E15+F12-F15 -> 246955.64 | G17: =F15+G12-G15 -> 525804.49 | H17: =G15+H12-H15 -> 350938.55 | I17: =H15+I12-I15 -> 463209.62 | J17: =I15+J12-J15 -> 376376.2 | K17: =J15+K12-K15 -> 188018.41 | L17: =K15+L12-L15 -> 41734.945 | ... AA17: =Z15+AA12-AA15 -> 567192.53
B18: WERKKAPITAAL-KPI'S
B19: DIO - voorraaddagen | C19: dg | D19: =IFERROR(D10/D9*s_dpm,0) -> 55 | E19: =IFERROR(E10/E9*s_dpm,0) -> 55 | F19: =IFERROR(F10/F9*s_dpm,0) -> 55 | G19: =IFERROR(G10/G9*s_dpm,0) -> 55 | H19: =IFERROR(H10/H9*s_dpm,0) -> 55 | I19: =IFERROR(I10/I9*s_dpm,0) -> 55 | J19: =IFERROR(J10/J9*s_dpm,0) -> 55 | K19: =IFERROR(K10/K9*s_dpm,0) -> 55 | ... AA19: =IFERROR(AA10/AA9*s_dpm,0) -> 55
B20: DSO - debiteurendagen | C20: dg | D20: =IFERROR(D14/D13*s_dpm,0) -> 45 | E20: =IFERROR(E14/E13*s_dpm,0) -> 45 | F20: =IFERROR(F14/F13*s_dpm,0) -> 45 | G20: =IFERROR(G14/G13*s_dpm,0) -> 45 | H20: =IFERROR(H14/H13*s_dpm,0) -> 45 | I20: =IFERROR(I14/I13*s_dpm,0) -> 45 | J20: =IFERROR(J14/J13*s_dpm,0) -> 45 | K20: =IFERROR(K14/K13*s_dpm,0) -> 45 | ... AA20: =IFERROR(AA14/AA13*s_dpm,0) -> 45
B21: DPO - crediteurendagen | C21: dg | D21: =IFERROR(D15/D12*s_dpm,0) -> 40 | E21: =IFERROR(E15/E12*s_dpm,0) -> 40 | F21: =IFERROR(F15/F12*s_dpm,0) -> 40 | G21: =IFERROR(G15/G12*s_dpm,0) -> 40 | H21: =IFERROR(H15/H12*s_dpm,0) -> 40 | I21: =IFERROR(I15/I12*s_dpm,0) -> 40 | J21: =IFERROR(J15/J12*s_dpm,0) -> 40 | K21: =IFERROR(K15/K12*s_dpm,0) -> 40 | ... AA21: =IFERROR(AA15/AA12*s_dpm,0) -> 40
B22: Cash Conversion Cycle (DIO+DSO-DPO) | C22: dg | D22: =D19+D20-D21 -> 60 | E22: =E19+E20-E21 -> 60 | F22: =F19+F20-F21 -> 60 | G22: =G19+G20-G21 -> 60 | H22: =H19+H20-H21 -> 60 | I22: =I19+I20-I21 -> 60 | J22: =J19+J20-J21 -> 60 | K22: =K19+K20-K21 -> 60 | ... AA22: =AA19+AA20-AA21 -> 60

Sheet 07 Personeel
B2: PERSONEEL - KOSTEN & FTE
B3: 07 Personeel · Maandloon + werkgeverslasten + vakantiegeld · what-if loonmutatie
B5: Maand | C5: Eenheid | D5: =EDATE(s_start,0) -> 46023 | E5: =EDATE(s_start,1) -> 46054 | F5: =EDATE(s_start,2) -> 46082 | G5: =EDATE(s_start,3) -> 46113 | H5: =EDATE(s_start,4) -> 46143 | I5: =EDATE(s_start,5) -> 46174 | J5: =EDATE(s_start,6) -> 46204 | K5: =EDATE(s_start,7) -> 46235 | L5: =EDATE(s_start,8) -> 46266 | M5: =EDATE(s_start,9) -> 46296 | N5: =EDATE(s_start,10) -> 46327 | O5: =EDATE(s_start,11) -> 46357 | P5: =EDATE(s_start,12) -> 46388 | Q5: =EDATE(s_start,13) -> 46419 | R5: =EDATE(s_start,14) -> 46447 | S5: =EDATE(s_start,15) -> 46478 | T5: =EDATE(s_start,16) -> 46508 | U5: =EDATE(s_start,17) -> 46539 | V5: =EDATE(s_start,18) -> 46569 | W5: =EDATE(s_start,19) -> 46600 | X5: =EDATE(s_start,20) -> 46631 | Y5: =EDATE(s_start,21) -> 46661 | Z5: =EDATE(s_start,22) -> 46692 | AA5: =EDATE(s_start,23) -> 46722
B6: Maandindex | D6: 1 | E6: 2 | F6: 3 | G6: 4 | H6: 5 | I6: 6 | J6: 7 | K6: 8 | L6: 9 | M6: 10 | N6: 11 | O6: 12 | P6: 13 | Q6: 14 | R6: 15 | S6: 16 | T6: 17 | U6: 18 | V6: 19 | W6: 20 | X6: 21 | Y6: 22 | Z6: 23 | AA6: 24
B7: Basis loonsom per maand | D7: 40000
B8: Werkgeverslasten % | D8: 0.28
B9: Vakantiegeld % (uitkering in mei) | D9: 0.08
B10: What-if loonmutatie % | D10: 0
B11: Aantal FTE | D11: 12
B13: Personeelskosten (kas-uit) | C13: € | D13: =($D$7*(1+$D$8))*(1+$D$10)*(1+p_kostengroei*(0)) -> 51200 | E13: =($D$7*(1+$D$8))*(1+$D$10)*(1+p_kostengroei*(0)) -> 51200 | F13: =($D$7*(1+$D$8))*(1+$D$10)*(1+p_kostengroei*(0)) -> 51200 | G13: =($D$7*(1+$D$8))*(1+$D$10)*(1+p_kostengroei*(0)) -> 51200 | H13: =($D$7*(1+$D$8)+$D$7*12*$D$9)*(1+$D$10)*(1+p_kostengroei*(0)) -> 89600 | I13: =($D$7*(1+$D$8))*(1+$D$10)*(1+p_kostengroei*(0)) -> 51200 | J13: =($D$7*(1+$D$8))*(1+$D$10)*(1+p_kostengroei*(0)) -> 51200 | K13: =($D$7*(1+$D$8))*(1+$D$10)*(1+p_kostengroei*(0)) -> 51200 | L13: =($D$7*(1+$D$8))*(1+$D$10)*(1+p_kostengroei*(0)) -> 51200 | M13: =($D$7*(1+$D$8))*(1+$D$10)*(1+p_kostengroei*(0)) -> 51200 | N13: =($D$7*(1+$D$8))*(1+$D$10)*(1+p_kostengroei*(0)) -> 51200 | O13: =($D$7*(1+$D$8))*(1+$D$10)*(1+p_kostengroei*(0)) -> 51200 | P13: =($D$7*(1+$D$8))*(1+$D$10)*(1+p_kostengroei*(1)) -> 51200 | Q13: =($D$7*(1+$D$8))*(1+$D$10)*(1+p_kostengroei*(1)) -> 51200 | R13: =($D$7*(1+$D$8))*(1+$D$10)*(1+p_kostengroei*(1)) -> 51200 | S13: =($D$7*(1+$D$8))*(1+$D$10)*(1+p_kostengroei*(1)) -> 51200 | T13: =($D$7*(1+$D$8)+$D$7*12*$D$9)*(1+$D$10)*(1+p_kostengroei*(1)) -> 89600 | U13: =($D$7*(1+$D$8))*(1+$D$10)*(1+p_kostengroei*(1)) -> 51200 | V13: =($D$7*(1+$D$8))*(1+$D$10)*(1+p_kostengroei*(1)) -> 51200 | W13: =($D$7*(1+$D$8))*(1+$D$10)*(1+p_kostengroei*(1)) -> 51200 | X13: =($D$7*(1+$D$8))*(1+$D$10)*(1+p_kostengroei*(1)) -> 51200 | Y13: =($D$7*(1+$D$8))*(1+$D$10)*(1+p_kostengroei*(1)) -> 51200 | Z13: =($D$7*(1+$D$8))*(1+$D$10)*(1+p_kostengroei*(1)) -> 51200 | AA13: =($D$7*(1+$D$8))*(1+$D$10)*(1+p_kostengroei*(1)) -> 51200
B14: Personeelskosten / omzet | C14: % | D14: =IFERROR(D13/'05 Omzet & marge'!D8,0) -> 0.14628571 | E14: =IFERROR(E13/'05 Omzet & marge'!E8,0) -> 0.14628571 | F14: =IFERROR(F13/'05 Omzet & marge'!F8,0) -> 0.12047059 | G14: =IFERROR(G13/'05 Omzet & marge'!G8,0) -> 0.12047059 | H14: =IFERROR(H13/'05 Omzet & marge'!H8,0) -> 0.19911111 | I14: =IFERROR(I13/'05 Omzet & marge'!I8,0) -> 0.12047059 | J14: =IFERROR(J13/'05 Omzet & marge'!J8,0) -> 0.14628571 | K14: =IFERROR(K13/'05 Omzet & marge'!K8,0) -> 0.17066667 | ... AA14: =IFERROR(AA13/'05 Omzet & marge'!AA8,0) -> 0.11377778
B15: FTE (constant, aanpasbaar) | C15: fte | D15: =$D$11 -> 12 | E15: =$D$11 -> 12 | F15: =$D$11 -> 12 | G15: =$D$11 -> 12 | H15: =$D$11 -> 12 | I15: =$D$11 -> 12 | J15: =$D$11 -> 12 | K15: =$D$11 -> 12 | ... AA15: =$D$11 -> 12

Sheet 08 Overige kosten
B2: OVERIGE OPERATIONELE KOSTEN
B3: 08 Overige kosten · Per categorie: vast bedrag per maand of % van omzet
B5: Maand | C5: Eenheid | D5: =EDATE(s_start,0) -> 46023 | E5: =EDATE(s_start,1) -> 46054 | F5: =EDATE(s_start,2) -> 46082 | G5: =EDATE(s_start,3) -> 46113 | H5: =EDATE(s_start,4) -> 46143 | I5: =EDATE(s_start,5) -> 46174 | J5: =EDATE(s_start,6) -> 46204 | K5: =EDATE(s_start,7) -> 46235 | L5: =EDATE(s_start,8) -> 46266 | M5: =EDATE(s_start,9) -> 46296 | N5: =EDATE(s_start,10) -> 46327 | O5: =EDATE(s_start,11) -> 46357 | P5: =EDATE(s_start,12) -> 46388 | Q5: =EDATE(s_start,13) -> 46419 | R5: =EDATE(s_start,14) -> 46447 | S5: =EDATE(s_start,15) -> 46478 | T5: =EDATE(s_start,16) -> 46508 | U5: =EDATE(s_start,17) -> 46539 | V5: =EDATE(s_start,18) -> 46569 | W5: =EDATE(s_start,19) -> 46600 | X5: =EDATE(s_start,20) -> 46631 | Y5: =EDATE(s_start,21) -> 46661 | Z5: =EDATE(s_start,22) -> 46692 | AA5: =EDATE(s_start,23) -> 46722
B6: Maandindex | D6: 1 | E6: 2 | F6: 3 | G6: 4 | H6: 5 | I6: 6 | J6: 7 | K6: 8 | L6: 9 | M6: 10 | N6: 11 | O6: 12 | P6: 13 | Q6: 14 | R6: 15 | S6: 16 | T6: 17 | U6: 18 | V6: 19 | W6: 20 | X6: 21 | Y6: 22 | Z6: 23 | AA6: 24
B7: KOSTENCATEGORIEËN (Type: V = vast/maand · P = % van omzet)
B8: Categorie | C8: Type | D8: Basis/maand | E8: % omzet | F8: BTW-plichtig?
B9: Huisvesting / huur | C9: V | D9: 8000 | E9: 0 | F9: JA
B10: Energie | C10: V | D10: 2800 | E10: 0 | F10: JA
B11: Transport / logistiek | C11: P | D11: 0 | E11: 0.02 | F11: JA
B12: Voertuigen | C12: V | D12: 3500 | E12: 0 | F12: JA
B13: Verzekeringen | C13: V | D13: 2000 | E13: 0 | F13: NEE
B14: Marketing / verkoop | C14: P | D14: 0 | E14: 0.01 | F14: JA
B15: IT | C15: V | D15: 2500 | E15: 0 | F15: JA
B16: Advies- / accountantskosten | C16: V | D16: 2000 | E16: 0 | F16: JA
B17: Overige algemene kosten | C17: V | D17: 3000 | E17: 0 | F17: JA
B19: Maand | C19: Eenheid | D19: =EDATE(s_start,0) -> 46023 | E19: =EDATE(s_start,1) -> 46054 | F19: =EDATE(s_start,2) -> 46082 | G19: =EDATE(s_start,3) -> 46113 | H19: =EDATE(s_start,4) -> 46143 | I19: =EDATE(s_start,5) -> 46174 | J19: =EDATE(s_start,6) -> 46204 | K19: =EDATE(s_start,7) -> 46235 | L19: =EDATE(s_start,8) -> 46266 | M19: =EDATE(s_start,9) -> 46296 | N19: =EDATE(s_start,10) -> 46327 | O19: =EDATE(s_start,11) -> 46357 | P19: =EDATE(s_start,12) -> 46388 | Q19: =EDATE(s_start,13) -> 46419 | R19: =EDATE(s_start,14) -> 46447 | S19: =EDATE(s_start,15) -> 46478 | T19: =EDATE(s_start,16) -> 46508 | U19: =EDATE(s_start,17) -> 46539 | V19: =EDATE(s_start,18) -> 46569 | W19: =EDATE(s_start,19) -> 46600 | X19: =EDATE(s_start,20) -> 46631 | Y19: =EDATE(s_start,21) -> 46661 | Z19: =EDATE(s_start,22) -> 46692 | AA19: =EDATE(s_start,23) -> 46722
B20: Huisvesting / huur | D20: =IF($C$9="V",$D$9*(1+p_kostengroei*0),$E$9*'05 Omzet & marge'!D8) -> 8000 | E20: =IF($C$9="V",$D$9*(1+p_kostengroei*0),$E$9*'05 Omzet & marge'!E8) -> 8000 | F20: =IF($C$9="V",$D$9*(1+p_kostengroei*0),$E$9*'05 Omzet & marge'!F8) -> 8000 | G20: =IF($C$9="V",$D$9*(1+p_kostengroei*0),$E$9*'05 Omzet & marge'!G8) -> 8000 | H20: =IF($C$9="V",$D$9*(1+p_kostengroei*0),$E$9*'05 Omzet & marge'!H8) -> 8000 | I20: =IF($C$9="V",$D$9*(1+p_kostengroei*0),$E$9*'05 Omzet & marge'!I8) -> 8000 | J20: =IF($C$9="V",$D$9*(1+p_kostengroei*0),$E$9*'05 Omzet & marge'!J8) -> 8000 | K20: =IF($C$9="V",$D$9*(1+p_kostengroei*0),$E$9*'05 Omzet & marge'!K8) -> 8000 | ... O20: =IF($C$9="V",$D$9*(1+p_kostengroei*0),$E$9*'05 Omzet & marge'!O8) -> 8000 | P20: =IF($C$9="V",$D$9*(1+p_kostengroei*1),$E$9*'05 Omzet & marge'!P8) -> 8000 | Q20: =IF($C$9="V",$D$9*(1+p_kostengroei*1),$E$9*'05 Omzet & marge'!Q8) -> 8000 | R20: =IF($C$9="V",$D$9*(1+p_kostengroei*1),$E$9*'05 Omzet & marge'!R8) -> 8000 | S20: =IF($C$9="V",$D$9*(1+p_kostengroei*1),$E$9*'05 Omzet & marge'!S8) -> 8000 | T20: =IF($C$9="V",$D$9*(1+p_kostengroei*1),$E$9*'05 Omzet & marge'!T8) -> 8000 | U20: =IF($C$9="V",$D$9*(1+p_kostengroei*1),$E$9*'05 Omzet & marge'!U8) -> 8000 | V20: =IF($C$9="V",$D$9*(1+p_kostengroei*1),$E$9*'05 Omzet & marge'!V8) -> 8000 | W20: =IF($C$9="V",$D$9*(1+p_kostengroei*1),$E$9*'05 Omzet & marge'!W8) -> 8000 | ... AA20: =IF($C$9="V",$D$9*(1+p_kostengroei*1),$E$9*'05 Omzet & marge'!AA8) -> 8000
B21: Energie | D21: =IF($C$10="V",$D$10*(1+p_kostengroei*0),$E$10*'05 Omzet & marge'!D8) -> 2800 | E21: =IF($C$10="V",$D$10*(1+p_kostengroei*0),$E$10*'05 Omzet & marge'!E8) -> 2800 | F21: =IF($C$10="V",$D$10*(1+p_kostengroei*0),$E$10*'05 Omzet & marge'!F8) -> 2800 | G21: =IF($C$10="V",$D$10*(1+p_kostengroei*0),$E$10*'05 Omzet & marge'!G8) -> 2800 | H21: =IF($C$10="V",$D$10*(1+p_kostengroei*0),$E$10*'05 Omzet & marge'!H8) -> 2800 | I21: =IF($C$10="V",$D$10*(1+p_kostengroei*0),$E$10*'05 Omzet & marge'!I8) -> 2800 | J21: =IF($C$10="V",$D$10*(1+p_kostengroei*0),$E$10*'05 Omzet & marge'!J8) -> 2800 | K21: =IF($C$10="V",$D$10*(1+p_kostengroei*0),$E$10*'05 Omzet & marge'!K8) -> 2800 | ... O21: =IF($C$10="V",$D$10*(1+p_kostengroei*0),$E$10*'05 Omzet & marge'!O8) -> 2800 | P21: =IF($C$10="V",$D$10*(1+p_kostengroei*1),$E$10*'05 Omzet & marge'!P8) -> 2800 | Q21: =IF($C$10="V",$D$10*(1+p_kostengroei*1),$E$10*'05 Omzet & marge'!Q8) -> 2800 | R21: =IF($C$10="V",$D$10*(1+p_kostengroei*1),$E$10*'05 Omzet & marge'!R8) -> 2800 | S21: =IF($C$10="V",$D$10*(1+p_kostengroei*1),$E$10*'05 Omzet & marge'!S8) -> 2800 | T21: =IF($C$10="V",$D$10*(1+p_kostengroei*1),$E$10*'05 Omzet & marge'!T8) -> 2800 | U21: =IF($C$10="V",$D$10*(1+p_kostengroei*1),$E$10*'05 Omzet & marge'!U8) -> 2800 | V21: =IF($C$10="V",$D$10*(1+p_kostengroei*1),$E$10*'05 Omzet & marge'!V8) -> 2800 | W21: =IF($C$10="V",$D$10*(1+p_kostengroei*1),$E$10*'05 Omzet & marge'!W8) -> 2800 | ... AA21: =IF($C$10="V",$D$10*(1+p_kostengroei*1),$E$10*'05 Omzet & marge'!AA8) -> 2800
B22: Transport / logistiek | D22: =IF($C$11="V",$D$11*(1+p_kostengroei*0),$E$11*'05 Omzet & marge'!D8) -> 7000 | E22: =IF($C$11="V",$D$11*(1+p_kostengroei*0),$E$11*'05 Omzet & marge'!E8) -> 7000 | F22: =IF($C$11="V",$D$11*(1+p_kostengroei*0),$E$11*'05 Omzet & marge'!F8) -> 8500 | G22: =IF($C$11="V",$D$11*(1+p_kostengroei*0),$E$11*'05 Omzet & marge'!G8) -> 8500 | H22: =IF($C$11="V",$D$11*(1+p_kostengroei*0),$E$11*'05 Omzet & marge'!H8) -> 9000 | I22: =IF($C$11="V",$D$11*(1+p_kostengroei*0),$E$11*'05 Omzet & marge'!I8) -> 8500 | J22: =IF($C$11="V",$D$11*(1+p_kostengroei*0),$E$11*'05 Omzet & marge'!J8) -> 7000 | K22: =IF($C$11="V",$D$11*(1+p_kostengroei*0),$E$11*'05 Omzet & marge'!K8) -> 6000 | ... O22: =IF($C$11="V",$D$11*(1+p_kostengroei*0),$E$11*'05 Omzet & marge'!O8) -> 9000 | P22: =IF($C$11="V",$D$11*(1+p_kostengroei*1),$E$11*'05 Omzet & marge'!P8) -> 7000 | Q22: =IF($C$11="V",$D$11*(1+p_kostengroei*1),$E$11*'05 Omzet & marge'!Q8) -> 7000 | R22: =IF($C$11="V",$D$11*(1+p_kostengroei*1),$E$11*'05 Omzet & marge'!R8) -> 8500 | S22: =IF($C$11="V",$D$11*(1+p_kostengroei*1),$E$11*'05 Omzet & marge'!S8) -> 8500 | T22: =IF($C$11="V",$D$11*(1+p_kostengroei*1),$E$11*'05 Omzet & marge'!T8) -> 9000 | U22: =IF($C$11="V",$D$11*(1+p_kostengroei*1),$E$11*'05 Omzet & marge'!U8) -> 8500 | V22: =IF($C$11="V",$D$11*(1+p_kostengroei*1),$E$11*'05 Omzet & marge'!V8) -> 7000 | W22: =IF($C$11="V",$D$11*(1+p_kostengroei*1),$E$11*'05 Omzet & marge'!W8) -> 6000 | ... AA22: =IF($C$11="V",$D$11*(1+p_kostengroei*1),$E$11*'05 Omzet & marge'!AA8) -> 9000
B23: Voertuigen | D23: =IF($C$12="V",$D$12*(1+p_kostengroei*0),$E$12*'05 Omzet & marge'!D8) -> 3500 | E23: =IF($C$12="V",$D$12*(1+p_kostengroei*0),$E$12*'05 Omzet & marge'!E8) -> 3500 | F23: =IF($C$12="V",$D$12*(1+p_kostengroei*0),$E$12*'05 Omzet & marge'!F8) -> 3500 | G23: =IF($C$12="V",$D$12*(1+p_kostengroei*0),$E$12*'05 Omzet & marge'!G8) -> 3500 | H23: =IF($C$12="V",$D$12*(1+p_kostengroei*0),$E$12*'05 Omzet & marge'!H8) -> 3500 | I23: =IF($C$12="V",$D$12*(1+p_kostengroei*0),$E$12*'05 Omzet & marge'!I8) -> 3500 | J23: =IF($C$12="V",$D$12*(1+p_kostengroei*0),$E$12*'05 Omzet & marge'!J8) -> 3500 | K23: =IF($C$12="V",$D$12*(1+p_kostengroei*0),$E$12*'05 Omzet & marge'!K8) -> 3500 | ... O23: =IF($C$12="V",$D$12*(1+p_kostengroei*0),$E$12*'05 Omzet & marge'!O8) -> 3500 | P23: =IF($C$12="V",$D$12*(1+p_kostengroei*1),$E$12*'05 Omzet & marge'!P8) -> 3500 | Q23: =IF($C$12="V",$D$12*(1+p_kostengroei*1),$E$12*'05 Omzet & marge'!Q8) -> 3500 | R23: =IF($C$12="V",$D$12*(1+p_kostengroei*1),$E$12*'05 Omzet & marge'!R8) -> 3500 | S23: =IF($C$12="V",$D$12*(1+p_kostengroei*1),$E$12*'05 Omzet & marge'!S8) -> 3500 | T23: =IF($C$12="V",$D$12*(1+p_kostengroei*1),$E$12*'05 Omzet & marge'!T8) -> 3500 | U23: =IF($C$12="V",$D$12*(1+p_kostengroei*1),$E$12*'05 Omzet & marge'!U8) -> 3500 | V23: =IF($C$12="V",$D$12*(1+p_kostengroei*1),$E$12*'05 Omzet & marge'!V8) -> 3500 | W23: =IF($C$12="V",$D$12*(1+p_kostengroei*1),$E$12*'05 Omzet & marge'!W8) -> 3500 | ... AA23: =IF($C$12="V",$D$12*(1+p_kostengroei*1),$E$12*'05 Omzet & marge'!AA8) -> 3500
B24: Verzekeringen | D24: =IF($C$13="V",$D$13*(1+p_kostengroei*0),$E$13*'05 Omzet & marge'!D8) -> 2000 | E24: =IF($C$13="V",$D$13*(1+p_kostengroei*0),$E$13*'05 Omzet & marge'!E8) -> 2000 | F24: =IF($C$13="V",$D$13*(1+p_kostengroei*0),$E$13*'05 Omzet & marge'!F8) -> 2000 | G24: =IF($C$13="V",$D$13*(1+p_kostengroei*0),$E$13*'05 Omzet & marge'!G8) -> 2000 | H24: =IF($C$13="V",$D$13*(1+p_kostengroei*0),$E$13*'05 Omzet & marge'!H8) -> 2000 | I24: =IF($C$13="V",$D$13*(1+p_kostengroei*0),$E$13*'05 Omzet & marge'!I8) -> 2000 | J24: =IF($C$13="V",$D$13*(1+p_kostengroei*0),$E$13*'05 Omzet & marge'!J8) -> 2000 | K24: =IF($C$13="V",$D$13*(1+p_kostengroei*0),$E$13*'05 Omzet & marge'!K8) -> 2000 | ... O24: =IF($C$13="V",$D$13*(1+p_kostengroei*0),$E$13*'05 Omzet & marge'!O8) -> 2000 | P24: =IF($C$13="V",$D$13*(1+p_kostengroei*1),$E$13*'05 Omzet & marge'!P8) -> 2000 | Q24: =IF($C$13="V",$D$13*(1+p_kostengroei*1),$E$13*'05 Omzet & marge'!Q8) -> 2000 | R24: =IF($C$13="V",$D$13*(1+p_kostengroei*1),$E$13*'05 Omzet & marge'!R8) -> 2000 | S24: =IF($C$13="V",$D$13*(1+p_kostengroei*1),$E$13*'05 Omzet & marge'!S8) -> 2000 | T24: =IF($C$13="V",$D$13*(1+p_kostengroei*1),$E$13*'05 Omzet & marge'!T8) -> 2000 | U24: =IF($C$13="V",$D$13*(1+p_kostengroei*1),$E$13*'05 Omzet & marge'!U8) -> 2000 | V24: =IF($C$13="V",$D$13*(1+p_kostengroei*1),$E$13*'05 Omzet & marge'!V8) -> 2000 | W24: =IF($C$13="V",$D$13*(1+p_kostengroei*1),$E$13*'05 Omzet & marge'!W8) -> 2000 | ... AA24: =IF($C$13="V",$D$13*(1+p_kostengroei*1),$E$13*'05 Omzet & marge'!AA8) -> 2000
B25: Marketing / verkoop | D25: =IF($C$14="V",$D$14*(1+p_kostengroei*0),$E$14*'05 Omzet & marge'!D8) -> 3500 | E25: =IF($C$14="V",$D$14*(1+p_kostengroei*0),$E$14*'05 Omzet & marge'!E8) -> 3500 | F25: =IF($C$14="V",$D$14*(1+p_kostengroei*0),$E$14*'05 Omzet & marge'!F8) -> 4250 | G25: =IF($C$14="V",$D$14*(1+p_kostengroei*0),$E$14*'05 Omzet & marge'!G8) -> 4250 | H25: =IF($C$14="V",$D$14*(1+p_kostengroei*0),$E$14*'05 Omzet & marge'!H8) -> 4500 | I25: =IF($C$14="V",$D$14*(1+p_kostengroei*0),$E$14*'05 Omzet & marge'!I8) -> 4250 | J25: =IF($C$14="V",$D$14*(1+p_kostengroei*0),$E$14*'05 Omzet & marge'!J8) -> 3500 | K25: =IF($C$14="V",$D$14*(1+p_kostengroei*0),$E$14*'05 Omzet & marge'!K8) -> 3000 | ... O25: =IF($C$14="V",$D$14*(1+p_kostengroei*0),$E$14*'05 Omzet & marge'!O8) -> 4500 | P25: =IF($C$14="V",$D$14*(1+p_kostengroei*1),$E$14*'05 Omzet & marge'!P8) -> 3500 | Q25: =IF($C$14="V",$D$14*(1+p_kostengroei*1),$E$14*'05 Omzet & marge'!Q8) -> 3500 | R25: =IF($C$14="V",$D$14*(1+p_kostengroei*1),$E$14*'05 Omzet & marge'!R8) -> 4250 | S25: =IF($C$14="V",$D$14*(1+p_kostengroei*1),$E$14*'05 Omzet & marge'!S8) -> 4250 | T25: =IF($C$14="V",$D$14*(1+p_kostengroei*1),$E$14*'05 Omzet & marge'!T8) -> 4500 | U25: =IF($C$14="V",$D$14*(1+p_kostengroei*1),$E$14*'05 Omzet & marge'!U8) -> 4250 | V25: =IF($C$14="V",$D$14*(1+p_kostengroei*1),$E$14*'05 Omzet & marge'!V8) -> 3500 | W25: =IF($C$14="V",$D$14*(1+p_kostengroei*1),$E$14*'05 Omzet & marge'!W8) -> 3000 | ... AA25: =IF($C$14="V",$D$14*(1+p_kostengroei*1),$E$14*'05 Omzet & marge'!AA8) -> 4500
B26: IT | D26: =IF($C$15="V",$D$15*(1+p_kostengroei*0),$E$15*'05 Omzet & marge'!D8) -> 2500 | E26: =IF($C$15="V",$D$15*(1+p_kostengroei*0),$E$15*'05 Omzet & marge'!E8) -> 2500 | F26: =IF($C$15="V",$D$15*(1+p_kostengroei*0),$E$15*'05 Omzet & marge'!F8) -> 2500 | G26: =IF($C$15="V",$D$15*(1+p_kostengroei*0),$E$15*'05 Omzet & marge'!G8) -> 2500 | H26: =IF($C$15="V",$D$15*(1+p_kostengroei*0),$E$15*'05 Omzet & marge'!H8) -> 2500 | I26: =IF($C$15="V",$D$15*(1+p_kostengroei*0),$E$15*'05 Omzet & marge'!I8) -> 2500 | J26: =IF($C$15="V",$D$15*(1+p_kostengroei*0),$E$15*'05 Omzet & marge'!J8) -> 2500 | K26: =IF($C$15="V",$D$15*(1+p_kostengroei*0),$E$15*'05 Omzet & marge'!K8) -> 2500 | ... O26: =IF($C$15="V",$D$15*(1+p_kostengroei*0),$E$15*'05 Omzet & marge'!O8) -> 2500 | P26: =IF($C$15="V",$D$15*(1+p_kostengroei*1),$E$15*'05 Omzet & marge'!P8) -> 2500 | Q26: =IF($C$15="V",$D$15*(1+p_kostengroei*1),$E$15*'05 Omzet & marge'!Q8) -> 2500 | R26: =IF($C$15="V",$D$15*(1+p_kostengroei*1),$E$15*'05 Omzet & marge'!R8) -> 2500 | S26: =IF($C$15="V",$D$15*(1+p_kostengroei*1),$E$15*'05 Omzet & marge'!S8) -> 2500 | T26: =IF($C$15="V",$D$15*(1+p_kostengroei*1),$E$15*'05 Omzet & marge'!T8) -> 2500 | U26: =IF($C$15="V",$D$15*(1+p_kostengroei*1),$E$15*'05 Omzet & marge'!U8) -> 2500 | V26: =IF($C$15="V",$D$15*(1+p_kostengroei*1),$E$15*'05 Omzet & marge'!V8) -> 2500 | W26: =IF($C$15="V",$D$15*(1+p_kostengroei*1),$E$15*'05 Omzet & marge'!W8) -> 2500 | ... AA26: =IF($C$15="V",$D$15*(1+p_kostengroei*1),$E$15*'05 Omzet & marge'!AA8) -> 2500
B27: Advies- / accountantskosten | D27: =IF($C$16="V",$D$16*(1+p_kostengroei*0),$E$16*'05 Omzet & marge'!D8) -> 2000 | E27: =IF($C$16="V",$D$16*(1+p_kostengroei*0),$E$16*'05 Omzet & marge'!E8) -> 2000 | F27: =IF($C$16="V",$D$16*(1+p_kostengroei*0),$E$16*'05 Omzet & marge'!F8) -> 2000 | G27: =IF($C$16="V",$D$16*(1+p_kostengroei*0),$E$16*'05 Omzet & marge'!G8) -> 2000 | H27: =IF($C$16="V",$D$16*(1+p_kostengroei*0),$E$16*'05 Omzet & marge'!H8) -> 2000 | I27: =IF($C$16="V",$D$16*(1+p_kostengroei*0),$E$16*'05 Omzet & marge'!I8) -> 2000 | J27: =IF($C$16="V",$D$16*(1+p_kostengroei*0),$E$16*'05 Omzet & marge'!J8) -> 2000 | K27: =IF($C$16="V",$D$16*(1+p_kostengroei*0),$E$16*'05 Omzet & marge'!K8) -> 2000 | ... O27: =IF($C$16="V",$D$16*(1+p_kostengroei*0),$E$16*'05 Omzet & marge'!O8) -> 2000 | P27: =IF($C$16="V",$D$16*(1+p_kostengroei*1),$E$16*'05 Omzet & marge'!P8) -> 2000 | Q27: =IF($C$16="V",$D$16*(1+p_kostengroei*1),$E$16*'05 Omzet & marge'!Q8) -> 2000 | R27: =IF($C$16="V",$D$16*(1+p_kostengroei*1),$E$16*'05 Omzet & marge'!R8) -> 2000 | S27: =IF($C$16="V",$D$16*(1+p_kostengroei*1),$E$16*'05 Omzet & marge'!S8) -> 2000 | T27: =IF($C$16="V",$D$16*(1+p_kostengroei*1),$E$16*'05 Omzet & marge'!T8) -> 2000 | U27: =IF($C$16="V",$D$16*(1+p_kostengroei*1),$E$16*'05 Omzet & marge'!U8) -> 2000 | V27: =IF($C$16="V",$D$16*(1+p_kostengroei*1),$E$16*'05 Omzet & marge'!V8) -> 2000 | W27: =IF($C$16="V",$D$16*(1+p_kostengroei*1),$E$16*'05 Omzet & marge'!W8) -> 2000 | ... AA27: =IF($C$16="V",$D$16*(1+p_kostengroei*1),$E$16*'05 Omzet & marge'!AA8) -> 2000
B28: Overige algemene kosten | D28: =IF($C$17="V",$D$17*(1+p_kostengroei*0),$E$17*'05 Omzet & marge'!D8) -> 3000 | E28: =IF($C$17="V",$D$17*(1+p_kostengroei*0),$E$17*'05 Omzet & marge'!E8) -> 3000 | F28: =IF($C$17="V",$D$17*(1+p_kostengroei*0),$E$17*'05 Omzet & marge'!F8) -> 3000 | G28: =IF($C$17="V",$D$17*(1+p_kostengroei*0),$E$17*'05 Omzet & marge'!G8) -> 3000 | H28: =IF($C$17="V",$D$17*(1+p_kostengroei*0),$E$17*'05 Omzet & marge'!H8) -> 3000 | I28: =IF($C$17="V",$D$17*(1+p_kostengroei*0),$E$17*'05 Omzet & marge'!I8) -> 3000 | J28: =IF($C$17="V",$D$17*(1+p_kostengroei*0),$E$17*'05 Omzet & marge'!J8) -> 3000 | K28: =IF($C$17="V",$D$17*(1+p_kostengroei*0),$E$17*'05 Omzet & marge'!K8) -> 3000 | ... O28: =IF($C$17="V",$D$17*(1+p_kostengroei*0),$E$17*'05 Omzet & marge'!O8) -> 3000 | P28: =IF($C$17="V",$D$17*(1+p_kostengroei*1),$E$17*'05 Omzet & marge'!P8) -> 3000 | Q28: =IF($C$17="V",$D$17*(1+p_kostengroei*1),$E$17*'05 Omzet & marge'!Q8) -> 3000 | R28: =IF($C$17="V",$D$17*(1+p_kostengroei*1),$E$17*'05 Omzet & marge'!R8) -> 3000 | S28: =IF($C$17="V",$D$17*(1+p_kostengroei*1),$E$17*'05 Omzet & marge'!S8) -> 3000 | T28: =IF($C$17="V",$D$17*(1+p_kostengroei*1),$E$17*'05 Omzet & marge'!T8) -> 3000 | U28: =IF($C$17="V",$D$17*(1+p_kostengroei*1),$E$17*'05 Omzet & marge'!U8) -> 3000 | V28: =IF($C$17="V",$D$17*(1+p_kostengroei*1),$E$17*'05 Omzet & marge'!V8) -> 3000 | W28: =IF($C$17="V",$D$17*(1+p_kostengroei*1),$E$17*'05 Omzet & marge'!W8) -> 3000 | ... AA28: =IF($C$17="V",$D$17*(1+p_kostengroei*1),$E$17*'05 Omzet & marge'!AA8) -> 3000
B29: TOTAAL overige kosten (kas-uit) | D29: =SUM(D20:D28) -> 34300 | E29: =SUM(E20:E28) -> 34300 | F29: =SUM(F20:F28) -> 36550 | G29: =SUM(G20:G28) -> 36550 | H29: =SUM(H20:H28) -> 37300 | I29: =SUM(I20:I28) -> 36550 | J29: =SUM(J20:J28) -> 34300 | K29: =SUM(K20:K28) -> 32800 | ... AA29: =SUM(AA20:AA28) -> 37300
B30: waarvan BTW-plichtig | D30: =IF($F$9="JA",D20,0)+IF($F$10="JA",D21,0)+IF($F$11="JA",D22,0)+IF($F$12="JA",D23,0)+IF($F$13="JA",D24,0)+IF($F$14="JA",D25,0)+IF($F$15="JA",D26,0)+IF($F$16="JA",D27,0)+IF($F$17="JA",D28,0) -> 32300 | E30: =IF($F$9="JA",E20,0)+IF($F$10="JA",E21,0)+IF($F$11="JA",E22,0)+IF($F$12="JA",E23,0)+IF($F$13="JA",E24,0)+IF($F$14="JA",E25,0)+IF($F$15="JA",E26,0)+IF($F$16="JA",E27,0)+IF($F$17="JA",E28,0) -> 32300 | F30: =IF($F$9="JA",F20,0)+IF($F$10="JA",F21,0)+IF($F$11="JA",F22,0)+IF($F$12="JA",F23,0)+IF($F$13="JA",F24,0)+IF($F$14="JA",F25,0)+IF($F$15="JA",F26,0)+IF($F$16="JA",F27,0)+IF($F$17="JA",F28,0) -> 34550 | G30: =IF($F$9="JA",G20,0)+IF($F$10="JA",G21,0)+IF($F$11="JA",G22,0)+IF($F$12="JA",G23,0)+IF($F$13="JA",G24,0)+IF($F$14="JA",G25,0)+IF($F$15="JA",G26,0)+IF($F$16="JA",G27,0)+IF($F$17="JA",G28,0) -> 34550 | H30: =IF($F$9="JA",H20,0)+IF($F$10="JA",H21,0)+IF($F$11="JA",H22,0)+IF($F$12="JA",H23,0)+IF($F$13="JA",H24,0)+IF($F$14="JA",H25,0)+IF($F$15="JA",H26,0)+IF($F$16="JA",H27,0)+IF($F$17="JA",H28,0) -> 35300 | I30: =IF($F$9="JA",I20,0)+IF($F$10="JA",I21,0)+IF($F$11="JA",I22,0)+IF($F$12="JA",I23,0)+IF($F$13="JA",I24,0)+IF($F$14="JA",I25,0)+IF($F$15="JA",I26,0)+IF($F$16="JA",I27,0)+IF($F$17="JA",I28,0) -> 34550 | J30: =IF($F$9="JA",J20,0)+IF($F$10="JA",J21,0)+IF($F$11="JA",J22,0)+IF($F$12="JA",J23,0)+IF($F$13="JA",J24,0)+IF($F$14="JA",J25,0)+IF($F$15="JA",J26,0)+IF($F$16="JA",J27,0)+IF($F$17="JA",J28,0) -> 32300 | K30: =IF($F$9="JA",K20,0)+IF($F$10="JA",K21,0)+IF($F$11="JA",K22,0)+IF($F$12="JA",K23,0)+IF($F$13="JA",K24,0)+IF($F$14="JA",K25,0)+IF($F$15="JA",K26,0)+IF($F$16="JA",K27,0)+IF($F$17="JA",K28,0) -> 30800 | ... AA30: =IF($F$9="JA",AA20,0)+IF($F$10="JA",AA21,0)+IF($F$11="JA",AA22,0)+IF($F$12="JA",AA23,0)+IF($F$13="JA",AA24,0)+IF($F$14="JA",AA25,0)+IF($F$15="JA",AA26,0)+IF($F$16="JA",AA27,0)+IF($F$17="JA",AA28,0) -> 35300

Sheet 09 Investeringen
B2: INVESTERINGEN (CAPEX)
B3: 09 Investeringen · Kas-impact op betaalmoment · afschrijving apart · scenario extra investering
B5: Maand | C5: Eenheid | D5: =EDATE(s_start,0) -> 46023 | E5: =EDATE(s_start,1) -> 46054 | F5: =EDATE(s_start,2) -> 46082 | G5: =EDATE(s_start,3) -> 46113 | H5: =EDATE(s_start,4) -> 46143 | I5: =EDATE(s_start,5) -> 46174 | J5: =EDATE(s_start,6) -> 46204 | K5: =EDATE(s_start,7) -> 46235 | L5: =EDATE(s_start,8) -> 46266 | M5: =EDATE(s_start,9) -> 46296 | N5: =EDATE(s_start,10) -> 46327 | O5: =EDATE(s_start,11) -> 46357 | P5: =EDATE(s_start,12) -> 46388 | Q5: =EDATE(s_start,13) -> 46419 | R5: =EDATE(s_start,14) -> 46447 | S5: =EDATE(s_start,15) -> 46478 | T5: =EDATE(s_start,16) -> 46508 | U5: =EDATE(s_start,17) -> 46539 | V5: =EDATE(s_start,18) -> 46569 | W5: =EDATE(s_start,19) -> 46600 | X5: =EDATE(s_start,20) -> 46631 | Y5: =EDATE(s_start,21) -> 46661 | Z5: =EDATE(s_start,22) -> 46692 | AA5: =EDATE(s_start,23) -> 46722
B6: Maandindex | D6: 1 | E6: 2 | F6: 3 | G6: 4 | H6: 5 | I6: 6 | J6: 7 | K6: 8 | L6: 9 | M6: 10 | N6: 11 | O6: 12 | P6: 13 | Q6: 14 | R6: 15 | S6: 16 | T6: 17 | U6: 18 | V6: 19 | W6: 20 | X6: 21 | Y6: 22 | Z6: 23 | AA6: 24
B7: INVESTERINGSSCHEMA
B8: Omschrijving | C8: Categorie | D8: Maand (1-24) | E8: Bedrag | F8: Afschr. jaren
B9: Vervanging heftruck | C9: Machines | D9: 4 | E9: 45000 | F9: 5
B10: Uitbreiding magazijnstelling | C10: Inventaris | D10: 9 | E10: 80000 | F10: 10
B11: IT / WMS-systeem | C11: IT | D11: 14 | E11: 60000 | F11: 5
B12: Bedrijfswagen | C12: Voertuigen | D12: 20 | E12: 40000 | F12: 5
B14: Maand | C14: Eenheid | D14: =EDATE(s_start,0) -> 46023 | E14: =EDATE(s_start,1) -> 46054 | F14: =EDATE(s_start,2) -> 46082 | G14: =EDATE(s_start,3) -> 46113 | H14: =EDATE(s_start,4) -> 46143 | I14: =EDATE(s_start,5) -> 46174 | J14: =EDATE(s_start,6) -> 46204 | K14: =EDATE(s_start,7) -> 46235 | L14: =EDATE(s_start,8) -> 46266 | M14: =EDATE(s_start,9) -> 46296 | N14: =EDATE(s_start,10) -> 46327 | O14: =EDATE(s_start,11) -> 46357 | P14: =EDATE(s_start,12) -> 46388 | Q14: =EDATE(s_start,13) -> 46419 | R14: =EDATE(s_start,14) -> 46447 | S14: =EDATE(s_start,15) -> 46478 | T14: =EDATE(s_start,16) -> 46508 | U14: =EDATE(s_start,17) -> 46539 | V14: =EDATE(s_start,18) -> 46569 | W14: =EDATE(s_start,19) -> 46600 | X14: =EDATE(s_start,20) -> 46631 | Y14: =EDATE(s_start,21) -> 46661 | Z14: =EDATE(s_start,22) -> 46692 | AA14: =EDATE(s_start,23) -> 46722
B15: CAPEX kas-uit (schema + scenario) | D15: =SUMIFS($E$9:$E$12,$D$9:$D$12,1)+IF(s_capexmnd=1,p_extra_capex,0) -> 0 | E15: =SUMIFS($E$9:$E$12,$D$9:$D$12,2)+IF(s_capexmnd=2,p_extra_capex,0) -> 0 | F15: =SUMIFS($E$9:$E$12,$D$9:$D$12,3)+IF(s_capexmnd=3,p_extra_capex,0) -> 0 | G15: =SUMIFS($E$9:$E$12,$D$9:$D$12,4)+IF(s_capexmnd=4,p_extra_capex,0) -> 45000 | H15: =SUMIFS($E$9:$E$12,$D$9:$D$12,5)+IF(s_capexmnd=5,p_extra_capex,0) -> 0 | I15: =SUMIFS($E$9:$E$12,$D$9:$D$12,6)+IF(s_capexmnd=6,p_extra_capex,0) -> 0 | J15: =SUMIFS($E$9:$E$12,$D$9:$D$12,7)+IF(s_capexmnd=7,p_extra_capex,0) -> 0 | K15: =SUMIFS($E$9:$E$12,$D$9:$D$12,8)+IF(s_capexmnd=8,p_extra_capex,0) -> 0 | L15: =SUMIFS($E$9:$E$12,$D$9:$D$12,9)+IF(s_capexmnd=9,p_extra_capex,0) -> 80000 | M15: =SUMIFS($E$9:$E$12,$D$9:$D$12,10)+IF(s_capexmnd=10,p_extra_capex,0) -> 0 | N15: =SUMIFS($E$9:$E$12,$D$9:$D$12,11)+IF(s_capexmnd=11,p_extra_capex,0) -> 0 | O15: =SUMIFS($E$9:$E$12,$D$9:$D$12,12)+IF(s_capexmnd=12,p_extra_capex,0) -> 0 | P15: =SUMIFS($E$9:$E$12,$D$9:$D$12,13)+IF(s_capexmnd=13,p_extra_capex,0) -> 0 | Q15: =SUMIFS($E$9:$E$12,$D$9:$D$12,14)+IF(s_capexmnd=14,p_extra_capex,0) -> 60000 | R15: =SUMIFS($E$9:$E$12,$D$9:$D$12,15)+IF(s_capexmnd=15,p_extra_capex,0) -> 0 | S15: =SUMIFS($E$9:$E$12,$D$9:$D$12,16)+IF(s_capexmnd=16,p_extra_capex,0) -> 0 | T15: =SUMIFS($E$9:$E$12,$D$9:$D$12,17)+IF(s_capexmnd=17,p_extra_capex,0) -> 0 | U15: =SUMIFS($E$9:$E$12,$D$9:$D$12,18)+IF(s_capexmnd=18,p_extra_capex,0) -> 0 | V15: =SUMIFS($E$9:$E$12,$D$9:$D$12,19)+IF(s_capexmnd=19,p_extra_capex,0) -> 0 | W15: =SUMIFS($E$9:$E$12,$D$9:$D$12,20)+IF(s_capexmnd=20,p_extra_capex,0) -> 40000 | X15: =SUMIFS($E$9:$E$12,$D$9:$D$12,21)+IF(s_capexmnd=21,p_extra_capex,0) -> 0 | Y15: =SUMIFS($E$9:$E$12,$D$9:$D$12,22)+IF(s_capexmnd=22,p_extra_capex,0) -> 0 | Z15: =SUMIFS($E$9:$E$12,$D$9:$D$12,23)+IF(s_capexmnd=23,p_extra_capex,0) -> 0 | AA15: =SUMIFS($E$9:$E$12,$D$9:$D$12,24)+IF(s_capexmnd=24,p_extra_capex,0) -> 0
B16: Afschrijving (P&L, geen kas) | D16: =IF($D$9<=1,$E$9/$F$9/12,0)+IF($D$10<=1,$E$10/$F$10/12,0)+IF($D$11<=1,$E$11/$F$11/12,0)+IF($D$12<=1,$E$12/$F$12/12,0) -> 0 | E16: =IF($D$9<=2,$E$9/$F$9/12,0)+IF($D$10<=2,$E$10/$F$10/12,0)+IF($D$11<=2,$E$11/$F$11/12,0)+IF($D$12<=2,$E$12/$F$12/12,0) -> 0 | F16: =IF($D$9<=3,$E$9/$F$9/12,0)+IF($D$10<=3,$E$10/$F$10/12,0)+IF($D$11<=3,$E$11/$F$11/12,0)+IF($D$12<=3,$E$12/$F$12/12,0) -> 0 | G16: =IF($D$9<=4,$E$9/$F$9/12,0)+IF($D$10<=4,$E$10/$F$10/12,0)+IF($D$11<=4,$E$11/$F$11/12,0)+IF($D$12<=4,$E$12/$F$12/12,0) -> 750 | H16: =IF($D$9<=5,$E$9/$F$9/12,0)+IF($D$10<=5,$E$10/$F$10/12,0)+IF($D$11<=5,$E$11/$F$11/12,0)+IF($D$12<=5,$E$12/$F$12/12,0) -> 750 | I16: =IF($D$9<=6,$E$9/$F$9/12,0)+IF($D$10<=6,$E$10/$F$10/12,0)+IF($D$11<=6,$E$11/$F$11/12,0)+IF($D$12<=6,$E$12/$F$12/12,0) -> 750 | J16: =IF($D$9<=7,$E$9/$F$9/12,0)+IF($D$10<=7,$E$10/$F$10/12,0)+IF($D$11<=7,$E$11/$F$11/12,0)+IF($D$12<=7,$E$12/$F$12/12,0) -> 750 | K16: =IF($D$9<=8,$E$9/$F$9/12,0)+IF($D$10<=8,$E$10/$F$10/12,0)+IF($D$11<=8,$E$11/$F$11/12,0)+IF($D$12<=8,$E$12/$F$12/12,0) -> 750 | L16: =IF($D$9<=9,$E$9/$F$9/12,0)+IF($D$10<=9,$E$10/$F$10/12,0)+IF($D$11<=9,$E$11/$F$11/12,0)+IF($D$12<=9,$E$12/$F$12/12,0) -> 1416.6667 | M16: =IF($D$9<=10,$E$9/$F$9/12,0)+IF($D$10<=10,$E$10/$F$10/12,0)+IF($D$11<=10,$E$11/$F$11/12,0)+IF($D$12<=10,$E$12/$F$12/12,0) -> 1416.6667 | N16: =IF($D$9<=11,$E$9/$F$9/12,0)+IF($D$10<=11,$E$10/$F$10/12,0)+IF($D$11<=11,$E$11/$F$11/12,0)+IF($D$12<=11,$E$12/$F$12/12,0) -> 1416.6667 | O16: =IF($D$9<=12,$E$9/$F$9/12,0)+IF($D$10<=12,$E$10/$F$10/12,0)+IF($D$11<=12,$E$11/$F$11/12,0)+IF($D$12<=12,$E$12/$F$12/12,0) -> 1416.6667 | P16: =IF($D$9<=13,$E$9/$F$9/12,0)+IF($D$10<=13,$E$10/$F$10/12,0)+IF($D$11<=13,$E$11/$F$11/12,0)+IF($D$12<=13,$E$12/$F$12/12,0) -> 1416.6667 | Q16: =IF($D$9<=14,$E$9/$F$9/12,0)+IF($D$10<=14,$E$10/$F$10/12,0)+IF($D$11<=14,$E$11/$F$11/12,0)+IF($D$12<=14,$E$12/$F$12/12,0) -> 2416.6667 | R16: =IF($D$9<=15,$E$9/$F$9/12,0)+IF($D$10<=15,$E$10/$F$10/12,0)+IF($D$11<=15,$E$11/$F$11/12,0)+IF($D$12<=15,$E$12/$F$12/12,0) -> 2416.6667 | S16: =IF($D$9<=16,$E$9/$F$9/12,0)+IF($D$10<=16,$E$10/$F$10/12,0)+IF($D$11<=16,$E$11/$F$11/12,0)+IF($D$12<=16,$E$12/$F$12/12,0) -> 2416.6667 | T16: =IF($D$9<=17,$E$9/$F$9/12,0)+IF($D$10<=17,$E$10/$F$10/12,0)+IF($D$11<=17,$E$11/$F$11/12,0)+IF($D$12<=17,$E$12/$F$12/12,0) -> 2416.6667 | U16: =IF($D$9<=18,$E$9/$F$9/12,0)+IF($D$10<=18,$E$10/$F$10/12,0)+IF($D$11<=18,$E$11/$F$11/12,0)+IF($D$12<=18,$E$12/$F$12/12,0) -> 2416.6667 | V16: =IF($D$9<=19,$E$9/$F$9/12,0)+IF($D$10<=19,$E$10/$F$10/12,0)+IF($D$11<=19,$E$11/$F$11/12,0)+IF($D$12<=19,$E$12/$F$12/12,0) -> 2416.6667 | W16: =IF($D$9<=20,$E$9/$F$9/12,0)+IF($D$10<=20,$E$10/$F$10/12,0)+IF($D$11<=20,$E$11/$F$11/12,0)+IF($D$12<=20,$E$12/$F$12/12,0) -> 3083.3333 | X16: =IF($D$9<=21,$E$9/$F$9/12,0)+IF($D$10<=21,$E$10/$F$10/12,0)+IF($D$11<=21,$E$11/$F$11/12,0)+IF($D$12<=21,$E$12/$F$12/12,0) -> 3083.3333 | Y16: =IF($D$9<=22,$E$9/$F$9/12,0)+IF($D$10<=22,$E$10/$F$10/12,0)+IF($D$11<=22,$E$11/$F$11/12,0)+IF($D$12<=22,$E$12/$F$12/12,0) -> 3083.3333 | Z16: =IF($D$9<=23,$E$9/$F$9/12,0)+IF($D$10<=23,$E$10/$F$10/12,0)+IF($D$11<=23,$E$11/$F$11/12,0)+IF($D$12<=23,$E$12/$F$12/12,0) -> 3083.3333 | AA16: =IF($D$9<=24,$E$9/$F$9/12,0)+IF($D$10<=24,$E$10/$F$10/12,0)+IF($D$11<=24,$E$11/$F$11/12,0)+IF($D$12<=24,$E$12/$F$12/12,0) -> 3083.3333

Sheet 10 Financiering
B2: FINANCIERING - LENINGEN, RC, LEASE, FACTORING
B3: 10 Financiering · Nieuwe financiering · aflossing · rente · beschikbare kredietruimte
B5: Maand | C5: Eenheid | D5: =EDATE(s_start,0) -> 46023 | E5: =EDATE(s_start,1) -> 46054 | F5: =EDATE(s_start,2) -> 46082 | G5: =EDATE(s_start,3) -> 46113 | H5: =EDATE(s_start,4) -> 46143 | I5: =EDATE(s_start,5) -> 46174 | J5: =EDATE(s_start,6) -> 46204 | K5: =EDATE(s_start,7) -> 46235 | L5: =EDATE(s_start,8) -> 46266 | M5: =EDATE(s_start,9) -> 46296 | N5: =EDATE(s_start,10) -> 46327 | O5: =EDATE(s_start,11) -> 46357 | P5: =EDATE(s_start,12) -> 46388 | Q5: =EDATE(s_start,13) -> 46419 | R5: =EDATE(s_start,14) -> 46447 | S5: =EDATE(s_start,15) -> 46478 | T5: =EDATE(s_start,16) -> 46508 | U5: =EDATE(s_start,17) -> 46539 | V5: =EDATE(s_start,18) -> 46569 | W5: =EDATE(s_start,19) -> 46600 | X5: =EDATE(s_start,20) -> 46631 | Y5: =EDATE(s_start,21) -> 46661 | Z5: =EDATE(s_start,22) -> 46692 | AA5: =EDATE(s_start,23) -> 46722
B6: Maandindex | D6: 1 | E6: 2 | F6: 3 | G6: 4 | H6: 5 | I6: 6 | J6: 7 | K6: 8 | L6: 9 | M6: 10 | N6: 11 | O6: 12 | P6: 13 | Q6: 14 | R6: 15 | S6: 16 | T6: 17 | U6: 18 | V6: 19 | W6: 20 | X6: 21 | Y6: 22 | Z6: 23 | AA6: 24
B7: Beginstand banklening | D7: =h_lening -> 900000
B8: Aflossing per maand (lineair) | D8: 10000
B9: RC-limiet | D9: =h_rc_limiet -> 500000
B11: Nieuwe financiering / opname (kas-in) | D11: 0 | E11: 0 | F11: 0 | G11: 0 | H11: 0 | I11: 0 | J11: 0 | K11: 0 | L11: 0 | M11: 0 | N11: 0 | O11: 0 | P11: 0 | Q11: 0 | R11: 0 | S11: 0 | T11: 0 | U11: 0 | V11: 0 | W11: 0 | X11: 0 | Y11: 0 | Z11: 0 | AA11: 0
B12: Aflossing lening (kas-uit) | D12: =MIN($D$8,$D$7) -> 10000 | E12: =MIN($D$8,D13) -> 10000 | F12: =MIN($D$8,E13) -> 10000 | G12: =MIN($D$8,F13) -> 10000 | H12: =MIN($D$8,G13) -> 10000 | I12: =MIN($D$8,H13) -> 10000 | J12: =MIN($D$8,I13) -> 10000 | K12: =MIN($D$8,J13) -> 10000 | L12: =MIN($D$8,K13) -> 10000 | ... AA12: =MIN($D$8,Z13) -> 10000
B13: Stand lening (eind maand) | D13: =$D$7-D12+D11 -> 890000 | E13: =D13-E12+E11 -> 880000 | F13: =E13-F12+F11 -> 870000 | G13: =F13-G12+G11 -> 860000 | H13: =G13-H12+H11 -> 850000 | I13: =H13-I12+I11 -> 840000 | J13: =I13-J12+J11 -> 830000 | K13: =J13-K12+K11 -> 820000 | L13: =K13-L12+L11 -> 810000 | ... AA13: =Z13-AA12+AA11 -> 660000
B14: Rente (kas-uit) | D14: =$D$7*p_rente/12 -> 4500 | E14: =D13*p_rente/12 -> 4450 | F14: =E13*p_rente/12 -> 4400 | G14: =F13*p_rente/12 -> 4350 | H14: =G13*p_rente/12 -> 4300 | I14: =H13*p_rente/12 -> 4250 | J14: =I13*p_rente/12 -> 4200 | K14: =J13*p_rente/12 -> 4150 | L14: =K13*p_rente/12 -> 4100 | ... AA14: =Z13*p_rente/12 -> 3350

Sheet 11 Belastingen
B2: BELASTINGEN - BTW, LOONHEFFING, VPB
B3: 11 Belastingen · Liquiditeitsplanning (geen fiscale aangifteberekening)
B5: Maand | C5: Eenheid | D5: =EDATE(s_start,0) -> 46023 | E5: =EDATE(s_start,1) -> 46054 | F5: =EDATE(s_start,2) -> 46082 | G5: =EDATE(s_start,3) -> 46113 | H5: =EDATE(s_start,4) -> 46143 | I5: =EDATE(s_start,5) -> 46174 | J5: =EDATE(s_start,6) -> 46204 | K5: =EDATE(s_start,7) -> 46235 | L5: =EDATE(s_start,8) -> 46266 | M5: =EDATE(s_start,9) -> 46296 | N5: =EDATE(s_start,10) -> 46327 | O5: =EDATE(s_start,11) -> 46357 | P5: =EDATE(s_start,12) -> 46388 | Q5: =EDATE(s_start,13) -> 46419 | R5: =EDATE(s_start,14) -> 46447 | S5: =EDATE(s_start,15) -> 46478 | T5: =EDATE(s_start,16) -> 46508 | U5: =EDATE(s_start,17) -> 46539 | V5: =EDATE(s_start,18) -> 46569 | W5: =EDATE(s_start,19) -> 46600 | X5: =EDATE(s_start,20) -> 46631 | Y5: =EDATE(s_start,21) -> 46661 | Z5: =EDATE(s_start,22) -> 46692 | AA5: =EDATE(s_start,23) -> 46722
B6: Maandindex | D6: 1 | E6: 2 | F6: 3 | G6: 4 | H6: 5 | I6: 6 | J6: 7 | K6: 8 | L6: 9 | M6: 10 | N6: 11 | O6: 12 | P6: 13 | Q6: 14 | R6: 15 | S6: 16 | T6: 17 | U6: 18 | V6: 19 | W6: 20 | X6: 21 | Y6: 22 | Z6: 23 | AA6: 24
B8: BTW over omzet (output) | D8: ='05 Omzet & marge'!D8*v_btw -> 73500 | E8: ='05 Omzet & marge'!E8*v_btw -> 73500 | F8: ='05 Omzet & marge'!F8*v_btw -> 89250 | G8: ='05 Omzet & marge'!G8*v_btw -> 89250 | H8: ='05 Omzet & marge'!H8*v_btw -> 94500 | I8: ='05 Omzet & marge'!I8*v_btw -> 89250 | J8: ='05 Omzet & marge'!J8*v_btw -> 73500 | K8: ='05 Omzet & marge'!K8*v_btw -> 63000 | ... AA8: ='05 Omzet & marge'!AA8*v_btw -> 94500
B9: BTW over inkoop+kosten+capex (input) | D9: =('06 Werkkapitaal'!D11+'08 Overige kosten'!D30+'09 Investeringen'!D15)*v_btw -> -2053.5789 | E9: =('06 Werkkapitaal'!E11+'08 Overige kosten'!E30+'09 Investeringen'!E15)*v_btw -> 59703 | F9: =('06 Werkkapitaal'!F11+'08 Overige kosten'!F30+'09 Investeringen'!F15)*v_btw -> 92031.947 | G9: =('06 Werkkapitaal'!G11+'08 Overige kosten'!G30+'09 Investeringen'!G15)*v_btw -> 80965.5 | H9: =('06 Werkkapitaal'!H11+'08 Overige kosten'!H30+'09 Investeringen'!H15)*v_btw -> 82291.816 | I9: =('06 Werkkapitaal'!I11+'08 Overige kosten'!I30+'09 Investeringen'!I15)*v_btw -> 64676.684 | J9: =('06 Werkkapitaal'!J11+'08 Overige kosten'!J30+'09 Investeringen'!J15)*v_btw -> 39186.553 | K9: =('06 Werkkapitaal'!K11+'08 Overige kosten'!K30+'09 Investeringen'!K15)*v_btw -> 38150.368 | ... AA9: =('06 Werkkapitaal'!AA11+'08 Overige kosten'!AA30+'09 Investeringen'!AA15)*v_btw -> 54936.553
B10: BTW-saldo (af te dragen) | D10: =D8-D9 -> 75553.579 | E10: =E8-E9 -> 13797 | F10: =F8-F9 -> -2781.9474 | G10: =G8-G9 -> 8284.5 | H10: =H8-H9 -> 12208.184 | I10: =I8-I9 -> 24573.316 | J10: =J8-J9 -> 34313.447 | K10: =K8-K9 -> 24849.632 | ... AA10: =AA8-AA9 -> 39563.447
B11: BTW-betaling (kas-uit) | D11: 0 | E11: =MAX(0,IF(s_btwregime="Maand",D10,0)) -> 0 | F11: =MAX(0,IF(s_btwregime="Maand",E10,0)) -> 0 | G11: =MAX(0,IF(s_btwregime="Maand",F10,IF(MOD(4-1,3)=0,SUM(D10:F10),0))) -> 86568.632 | H11: =MAX(0,IF(s_btwregime="Maand",G10,IF(MOD(5-1,3)=0,SUM(E10:G10),0))) -> 0 | I11: =MAX(0,IF(s_btwregime="Maand",H10,IF(MOD(6-1,3)=0,SUM(F10:H10),0))) -> 0 | J11: =MAX(0,IF(s_btwregime="Maand",I10,IF(MOD(7-1,3)=0,SUM(G10:I10),0))) -> 45066 | K11: =MAX(0,IF(s_btwregime="Maand",J10,IF(MOD(8-1,3)=0,SUM(H10:J10),0))) -> 0 | L11: =MAX(0,IF(s_btwregime="Maand",K10,IF(MOD(9-1,3)=0,SUM(I10:K10),0))) -> 0 | M11: =MAX(0,IF(s_btwregime="Maand",L10,IF(MOD(10-1,3)=0,SUM(J10:L10),0))) -> 20377.184 | N11: =MAX(0,IF(s_btwregime="Maand",M10,IF(MOD(11-1,3)=0,SUM(K10:M10),0))) -> 0 | O11: =MAX(0,IF(s_btwregime="Maand",N10,IF(MOD(12-1,3)=0,SUM(L10:N10),0))) -> 0 | P11: =MAX(0,IF(s_btwregime="Maand",O10,IF(MOD(13-1,3)=0,SUM(M10:O10),0))) -> 63703.5 | Q11: =MAX(0,IF(s_btwregime="Maand",P10,IF(MOD(14-1,3)=0,SUM(N10:P10),0))) -> 0 | R11: =MAX(0,IF(s_btwregime="Maand",Q10,IF(MOD(15-1,3)=0,SUM(O10:Q10),0))) -> 0 | S11: =MAX(0,IF(s_btwregime="Maand",R10,IF(MOD(16-1,3)=0,SUM(P10:R10),0))) -> 39567.316 | T11: =MAX(0,IF(s_btwregime="Maand",S10,IF(MOD(17-1,3)=0,SUM(Q10:S10),0))) -> 0 | U11: =MAX(0,IF(s_btwregime="Maand",T10,IF(MOD(18-1,3)=0,SUM(R10:T10),0))) -> 0 | V11: =MAX(0,IF(s_btwregime="Maand",U10,IF(MOD(19-1,3)=0,SUM(S10:U10),0))) -> 54516 | W11: =MAX(0,IF(s_btwregime="Maand",V10,IF(MOD(20-1,3)=0,SUM(T10:V10),0))) -> 0 | X11: =MAX(0,IF(s_btwregime="Maand",W10,IF(MOD(21-1,3)=0,SUM(U10:W10),0))) -> 0 | Y11: =MAX(0,IF(s_btwregime="Maand",X10,IF(MOD(22-1,3)=0,SUM(V10:X10),0))) -> 28777.184 | Z11: =MAX(0,IF(s_btwregime="Maand",Y10,IF(MOD(23-1,3)=0,SUM(W10:Y10),0))) -> 0 | AA11: =MAX(0,IF(s_btwregime="Maand",Z10,IF(MOD(24-1,3)=0,SUM(X10:Z10),0))) -> 0
B13: Loonheffing (MEMO - zit al in personeelskosten) | D13: ='07 Personeel'!D13*0.35 -> 17920 | E13: ='07 Personeel'!E13*0.35 -> 17920 | F13: ='07 Personeel'!F13*0.35 -> 17920 | G13: ='07 Personeel'!G13*0.35 -> 17920 | H13: ='07 Personeel'!H13*0.35 -> 31360 | I13: ='07 Personeel'!I13*0.35 -> 17920 | J13: ='07 Personeel'!J13*0.35 -> 17920 | K13: ='07 Personeel'!K13*0.35 -> 17920 | ... AA13: ='07 Personeel'!AA13*0.35 -> 17920
B14: VPB-betaling (kas-uit, per kwartaal) | D14: =IF(MOD(1,3)=0,8000,0) -> 0 | E14: =IF(MOD(2,3)=0,8000,0) -> 0 | F14: =IF(MOD(3,3)=0,8000,0) -> 8000 | G14: =IF(MOD(4,3)=0,8000,0) -> 0 | H14: =IF(MOD(5,3)=0,8000,0) -> 0 | I14: =IF(MOD(6,3)=0,8000,0) -> 8000 | J14: =IF(MOD(7,3)=0,8000,0) -> 0 | K14: =IF(MOD(8,3)=0,8000,0) -> 0 | L14: =IF(MOD(9,3)=0,8000,0) -> 8000 | M14: =IF(MOD(10,3)=0,8000,0) -> 0 | N14: =IF(MOD(11,3)=0,8000,0) -> 0 | O14: =IF(MOD(12,3)=0,8000,0) -> 8000 | P14: =IF(MOD(13,3)=0,8000,0) -> 0 | Q14: =IF(MOD(14,3)=0,8000,0) -> 0 | R14: =IF(MOD(15,3)=0,8000,0) -> 8000 | S14: =IF(MOD(16,3)=0,8000,0) -> 0 | T14: =IF(MOD(17,3)=0,8000,0) -> 0 | U14: =IF(MOD(18,3)=0,8000,0) -> 8000 | V14: =IF(MOD(19,3)=0,8000,0) -> 0 | W14: =IF(MOD(20,3)=0,8000,0) -> 0 | X14: =IF(MOD(21,3)=0,8000,0) -> 8000 | Y14: =IF(MOD(22,3)=0,8000,0) -> 0 | Z14: =IF(MOD(23,3)=0,8000,0) -> 0 | AA14: =IF(MOD(24,3)=0,8000,0) -> 8000
B15: Totaal belastingen excl. BTW (kas-uit) = VPB | D15: =D14 -> 0 | E15: =E14 -> 0 | F15: =F14 -> 8000 | G15: =G14 -> 0 | H15: =H14 -> 0 | I15: =I14 -> 8000 | J15: =J14 -> 0 | K15: =K14 -> 0 | ... AA15: =AA14 -> 8000

Sheet 12 Liquiditeitsprognose
B2: LIQUIDITEITSPROGNOSE - 24 MAANDEN
B3: 12 Liquiditeitsprognose · Begin + inkomend - uitgaand = eind · buffer · financieringsbehoefte
B5: Maand | C5: Eenheid | D5: =EDATE(s_start,0) -> 46023 | E5: =EDATE(s_start,1) -> 46054 | F5: =EDATE(s_start,2) -> 46082 | G5: =EDATE(s_start,3) -> 46113 | H5: =EDATE(s_start,4) -> 46143 | I5: =EDATE(s_start,5) -> 46174 | J5: =EDATE(s_start,6) -> 46204 | K5: =EDATE(s_start,7) -> 46235 | L5: =EDATE(s_start,8) -> 46266 | M5: =EDATE(s_start,9) -> 46296 | N5: =EDATE(s_start,10) -> 46327 | O5: =EDATE(s_start,11) -> 46357 | P5: =EDATE(s_start,12) -> 46388 | Q5: =EDATE(s_start,13) -> 46419 | R5: =EDATE(s_start,14) -> 46447 | S5: =EDATE(s_start,15) -> 46478 | T5: =EDATE(s_start,16) -> 46508 | U5: =EDATE(s_start,17) -> 46539 | V5: =EDATE(s_start,18) -> 46569 | W5: =EDATE(s_start,19) -> 46600 | X5: =EDATE(s_start,20) -> 46631 | Y5: =EDATE(s_start,21) -> 46661 | Z5: =EDATE(s_start,22) -> 46692 | AA5: =EDATE(s_start,23) -> 46722
B6: Maandindex | D6: 1 | E6: 2 | F6: 3 | G6: 4 | H6: 5 | I6: 6 | J6: 7 | K6: 8 | L6: 9 | M6: 10 | N6: 11 | O6: 12 | P6: 13 | Q6: 14 | R6: 15 | S6: 16 | T6: 17 | U6: 18 | V6: 19 | W6: 20 | X6: 21 | Y6: 22 | Z6: 23 | AA6: 24
B8: BEGINLIQUIDITEIT | D8: =s_bank0 -> 300000 | E8: =D25 -> 76529.965 | F8: =E25 -> 559364.61 | G8: =F25 -> 578175.09 | H8: =G25 -> 328951.96 | I8: =H25 -> 332535.45 | J8: =I25 -> 278353.8 | K8: =J25 -> 311045.48 | L8: =K25 -> 473432.99 | ... AA8: =Z25 -> 236144.26
B9: + Ontvangsten van klanten | D9: ='06 Werkkapitaal'!D16 -> 396608.55 | E9: ='06 Werkkapitaal'!E16 -> 423500 | F9: ='06 Werkkapitaal'!F16 -> 379916.12 | G9: ='06 Werkkapitaal'!G16 -> 514250 | H9: ='06 Werkkapitaal'!H16 -> 499722.04 | I9: ='06 Werkkapitaal'!I16 -> 559027.96 | J9: ='06 Werkkapitaal'!J16 -> 557833.88 | K9: ='06 Werkkapitaal'!K16 -> 452555.92 | ... AA9: ='06 Werkkapitaal'!AA16 -> 678833.88
B10: + Overige ontvangsten | D10: ='04 Input prognose'!D9 -> 0 | E10: ='04 Input prognose'!E9 -> 0 | F10: ='04 Input prognose'!F9 -> 0 | G10: ='04 Input prognose'!G9 -> 0 | H10: ='04 Input prognose'!H9 -> 0 | I10: ='04 Input prognose'!I9 -> 0 | J10: ='04 Input prognose'!J9 -> 0 | K10: ='04 Input prognose'!K9 -> 0 | ... AA10: ='04 Input prognose'!AA9 -> 0
B11: + Nieuwe financiering / opname | D11: ='10 Financiering'!D11 -> 0 | E11: ='10 Financiering'!E11 -> 0 | F11: ='10 Financiering'!F11 -> 0 | G11: ='10 Financiering'!G11 -> 0 | H11: ='10 Financiering'!H11 -> 0 | I11: ='10 Financiering'!I11 -> 0 | J11: ='10 Financiering'!J11 -> 0 | K11: ='10 Financiering'!K11 -> 0 | ... AA11: ='10 Financiering'!AA11 -> 0
B12: TOTAAL INKOMEND | D12: =D9+D10+D11 -> 396608.55 | E12: =E9+E10+E11 -> 423500 | F12: =F9+F10+F11 -> 379916.12 | G12: =G9+G10+G11 -> 514250 | H12: =H9+H10+H11 -> 499722.04 | I12: =I9+I10+I11 -> 559027.96 | J12: =J9+J10+J11 -> 557833.88 | K12: =K9+K10+K11 -> 452555.92 | ... AA12: =AA9+AA10+AA11 -> 678833.88
B13: - Betalingen leveranciers | D13: ='06 Werkkapitaal'!D17 -> 516078.59 | E13: ='06 Werkkapitaal'!E17 -> -163284.64 | F13: ='06 Werkkapitaal'!F17 -> 246955.64 | G13: ='06 Werkkapitaal'!G17 -> 525804.49 | H13: ='06 Werkkapitaal'!H17 -> 350938.55 | I13: ='06 Werkkapitaal'!I17 -> 463209.62 | J13: ='06 Werkkapitaal'!J17 -> 376376.2 | K13: ='06 Werkkapitaal'!K17 -> 188018.41 | ... AA13: ='06 Werkkapitaal'!AA17 -> 567192.53
B14: - Personeel | D14: ='07 Personeel'!D13 -> 51200 | E14: ='07 Personeel'!E13 -> 51200 | F14: ='07 Personeel'!F13 -> 51200 | G14: ='07 Personeel'!G13 -> 51200 | H14: ='07 Personeel'!H13 -> 89600 | I14: ='07 Personeel'!I13 -> 51200 | J14: ='07 Personeel'!J13 -> 51200 | K14: ='07 Personeel'!K13 -> 51200 | ... AA14: ='07 Personeel'!AA13 -> 51200
B15: - Overige kosten | D15: ='08 Overige kosten'!D29 -> 34300 | E15: ='08 Overige kosten'!E29 -> 34300 | F15: ='08 Overige kosten'!F29 -> 36550 | G15: ='08 Overige kosten'!G29 -> 36550 | H15: ='08 Overige kosten'!H29 -> 37300 | I15: ='08 Overige kosten'!I29 -> 36550 | J15: ='08 Overige kosten'!J29 -> 34300 | K15: ='08 Overige kosten'!K29 -> 32800 | ... AA15: ='08 Overige kosten'!AA29 -> 37300
B16: - BTW | D16: ='11 Belastingen'!D11 -> 0 | E16: ='11 Belastingen'!E11 -> 0 | F16: ='11 Belastingen'!F11 -> 0 | G16: ='11 Belastingen'!G11 -> 86568.632 | H16: ='11 Belastingen'!H11 -> 0 | I16: ='11 Belastingen'!I11 -> 0 | J16: ='11 Belastingen'!J11 -> 45066 | K16: ='11 Belastingen'!K11 -> 0 | ... AA16: ='11 Belastingen'!AA11 -> 0
B17: - VPB (vennootschapsbelasting) | D17: ='11 Belastingen'!D15 -> 0 | E17: ='11 Belastingen'!E15 -> 0 | F17: ='11 Belastingen'!F15 -> 8000 | G17: ='11 Belastingen'!G15 -> 0 | H17: ='11 Belastingen'!H15 -> 0 | I17: ='11 Belastingen'!I15 -> 8000 | J17: ='11 Belastingen'!J15 -> 0 | K17: ='11 Belastingen'!K15 -> 0 | ... AA17: ='11 Belastingen'!AA15 -> 8000
B18: - Investeringen (capex) | D18: ='09 Investeringen'!D15 -> 0 | E18: ='09 Investeringen'!E15 -> 0 | F18: ='09 Investeringen'!F15 -> 0 | G18: ='09 Investeringen'!G15 -> 45000 | H18: ='09 Investeringen'!H15 -> 0 | I18: ='09 Investeringen'!I15 -> 0 | J18: ='09 Investeringen'!J15 -> 0 | K18: ='09 Investeringen'!K15 -> 0 | ... AA18: ='09 Investeringen'!AA15 -> 0
B19: - Rente | D19: ='10 Financiering'!D14 -> 4500 | E19: ='10 Financiering'!E14 -> 4450 | F19: ='10 Financiering'!F14 -> 4400 | G19: ='10 Financiering'!G14 -> 4350 | H19: ='10 Financiering'!H14 -> 4300 | I19: ='10 Financiering'!I14 -> 4250 | J19: ='10 Financiering'!J14 -> 4200 | K19: ='10 Financiering'!K14 -> 4150 | ... AA19: ='10 Financiering'!AA14 -> 3350
B20: - Aflossingen | D20: ='10 Financiering'!D12 -> 10000 | E20: ='10 Financiering'!E12 -> 10000 | F20: ='10 Financiering'!F12 -> 10000 | G20: ='10 Financiering'!G12 -> 10000 | H20: ='10 Financiering'!H12 -> 10000 | I20: ='10 Financiering'!I12 -> 10000 | J20: ='10 Financiering'!J12 -> 10000 | K20: ='10 Financiering'!K12 -> 10000 | ... AA20: ='10 Financiering'!AA12 -> 10000
B21: - Dividend / privé | D21: ='04 Input prognose'!D11 -> 4000 | E21: ='04 Input prognose'!E11 -> 4000 | F21: ='04 Input prognose'!F11 -> 4000 | G21: ='04 Input prognose'!G11 -> 4000 | H21: ='04 Input prognose'!H11 -> 4000 | I21: ='04 Input prognose'!I11 -> 40000 | J21: ='04 Input prognose'!J11 -> 4000 | K21: ='04 Input prognose'!K11 -> 4000 | ... AA21: ='04 Input prognose'!AA11 -> 4000
B22: - Overige uitgaven | D22: ='04 Input prognose'!D10 -> 0 | E22: ='04 Input prognose'!E10 -> 0 | F22: ='04 Input prognose'!F10 -> 0 | G22: ='04 Input prognose'!G10 -> 0 | H22: ='04 Input prognose'!H10 -> 0 | I22: ='04 Input prognose'!I10 -> 0 | J22: ='04 Input prognose'!J10 -> 0 | K22: ='04 Input prognose'!K10 -> 0 | ... AA22: ='04 Input prognose'!AA10 -> 0
B23: TOTAAL UITGAAND | D23: =SUM(D13:D22) -> 620078.59 | E23: =SUM(E13:E22) -> -59334.64 | F23: =SUM(F13:F22) -> 361105.64 | G23: =SUM(G13:G22) -> 763473.13 | H23: =SUM(H13:H22) -> 496138.55 | I23: =SUM(I13:I22) -> 613209.62 | J23: =SUM(J13:J22) -> 525142.2 | K23: =SUM(K13:K22) -> 290168.41 | ... AA23: =SUM(AA13:AA22) -> 681042.53
B24: NETTO KASSTROOM | D24: =D12-D23 -> -223470.03 | E24: =E12-E23 -> 482834.64 | F24: =F12-F23 -> 18810.481 | G24: =G12-G23 -> -249223.13 | H24: =H12-H23 -> 3583.4938 | I24: =I12-I23 -> -54181.659 | J24: =J12-J23 -> 32691.684 | K24: =K12-K23 -> 162387.51 | ... AA24: =AA12-AA23 -> -2208.6461
B25: EINDLIQUIDITEIT | D25: =D8+D24 -> 76529.965 | E25: =E8+E24 -> 559364.61 | F25: =F8+F24 -> 578175.09 | G25: =G8+G24 -> 328951.96 | H25: =H8+H24 -> 332535.45 | I25: =I8+I24 -> 278353.8 | J25: =J8+J24 -> 311045.48 | K25: =K8+K24 -> 473432.99 | ... AA25: =AA8+AA24 -> 233935.61
B27: Minimale buffer | D27: =s_buffer -> 100000 | E27: =s_buffer -> 100000 | F27: =s_buffer -> 100000 | G27: =s_buffer -> 100000 | H27: =s_buffer -> 100000 | I27: =s_buffer -> 100000 | J27: =s_buffer -> 100000 | K27: =s_buffer -> 100000 | ... AA27: =s_buffer -> 100000
B28: Vrije liquiditeit (eind - buffer) | D28: =D25-D27 -> -23470.035 | E28: =E25-E27 -> 459364.61 | F28: =F25-F27 -> 478175.09 | G28: =G25-G27 -> 228951.96 | H28: =H25-H27 -> 232535.45 | I28: =I25-I27 -> 178353.8 | J28: =J25-J27 -> 211045.48 | K28: =K25-K27 -> 373432.99 | ... AA28: =AA25-AA27 -> 133935.61
B29: Financieringsbehoefte (tekort t.o.v. buffer) | D29: =MAX(0,D27-D25) -> 23470.035 | E29: =MAX(0,E27-E25) -> 0 | F29: =MAX(0,F27-F25) -> 0 | G29: =MAX(0,G27-G25) -> 0 | H29: =MAX(0,H27-H25) -> 0 | I29: =MAX(0,I27-I25) -> 0 | J29: =MAX(0,J27-J25) -> 0 | K29: =MAX(0,K27-K25) -> 0 | ... AA29: =MAX(0,AA27-AA25) -> 0
B30: Overige kasstroom (excl. deb/cred) - hulpregel | D30: =D24-D9+D13 -> -104000 | E30: =E24-E9+E13 -> -103950 | F30: =F24-F9+F13 -> -114150 | G30: =G24-G9+G13 -> -237668.63 | H30: =H24-H9+H13 -> -145200 | I30: =I24-I9+I13 -> -150000 | J30: =J24-J9+J13 -> -148766 | K30: =K24-K9+K13 -> -102150 | ... AA30: =AA24-AA9+AA13 -> -113850

Sheet 13 Scenarioanalyse
B2: SCENARIOANALYSE - BASE / BEST / WORST
B3: 13 Scenarioanalyse · Omzet-, marge- & werkkapitaaleffect per scenario · overige kaslijnen = actief model
B5: Maand | C5: Eenheid | D5: =EDATE(s_start,0) -> 46023 | E5: =EDATE(s_start,1) -> 46054 | F5: =EDATE(s_start,2) -> 46082 | G5: =EDATE(s_start,3) -> 46113 | H5: =EDATE(s_start,4) -> 46143 | I5: =EDATE(s_start,5) -> 46174 | J5: =EDATE(s_start,6) -> 46204 | K5: =EDATE(s_start,7) -> 46235 | L5: =EDATE(s_start,8) -> 46266 | M5: =EDATE(s_start,9) -> 46296 | N5: =EDATE(s_start,10) -> 46327 | O5: =EDATE(s_start,11) -> 46357 | P5: =EDATE(s_start,12) -> 46388 | Q5: =EDATE(s_start,13) -> 46419 | R5: =EDATE(s_start,14) -> 46447 | S5: =EDATE(s_start,15) -> 46478 | T5: =EDATE(s_start,16) -> 46508 | U5: =EDATE(s_start,17) -> 46539 | V5: =EDATE(s_start,18) -> 46569 | W5: =EDATE(s_start,19) -> 46600 | X5: =EDATE(s_start,20) -> 46631 | Y5: =EDATE(s_start,21) -> 46661 | Z5: =EDATE(s_start,22) -> 46692 | AA5: =EDATE(s_start,23) -> 46722
B6: Maandindex | D6: 1 | E6: 2 | F6: 3 | G6: 4 | H6: 5 | I6: 6 | J6: 7 | K6: 8 | L6: 9 | M6: 10 | N6: 11 | O6: 12 | P6: 13 | Q6: 14 | R6: 15 | S6: 16 | T6: 17 | U6: 18 | V6: 19 | W6: 20 | X6: 21 | Y6: 22 | Z6: 23 | AA6: 24
B8: SCENARIO: Base
B9: Omzet (excl. BTW) | D9: ='04 Input prognose'!D$8*s_omzet_jaar*(1+'02 Instellingen'!$D$21) -> 350000 | E9: ='04 Input prognose'!E$8*s_omzet_jaar*(1+'02 Instellingen'!$D$21) -> 350000 | F9: ='04 Input prognose'!F$8*s_omzet_jaar*(1+'02 Instellingen'!$D$21) -> 425000 | G9: ='04 Input prognose'!G$8*s_omzet_jaar*(1+'02 Instellingen'!$D$21) -> 425000 | H9: ='04 Input prognose'!H$8*s_omzet_jaar*(1+'02 Instellingen'!$D$21) -> 450000 | I9: ='04 Input prognose'!I$8*s_omzet_jaar*(1+'02 Instellingen'!$D$21) -> 425000 | J9: ='04 Input prognose'!J$8*s_omzet_jaar*(1+'02 Instellingen'!$D$21) -> 350000 | K9: ='04 Input prognose'!K$8*s_omzet_jaar*(1+'02 Instellingen'!$D$21) -> 300000 | ... AA9: ='04 Input prognose'!AA$8*s_omzet_jaar*(1+'02 Instellingen'!$D$21) -> 450000
B10: Inkoopwaarde omzet | D10: =D9*(1-(s_margin+'02 Instellingen'!$D$22)) -> 252000 | E10: =E9*(1-(s_margin+'02 Instellingen'!$D$22)) -> 252000 | F10: =F9*(1-(s_margin+'02 Instellingen'!$D$22)) -> 306000 | G10: =G9*(1-(s_margin+'02 Instellingen'!$D$22)) -> 306000 | H10: =H9*(1-(s_margin+'02 Instellingen'!$D$22)) -> 324000 | I10: =I9*(1-(s_margin+'02 Instellingen'!$D$22)) -> 306000 | J10: =J9*(1-(s_margin+'02 Instellingen'!$D$22)) -> 252000 | K10: =K9*(1-(s_margin+'02 Instellingen'!$D$22)) -> 216000 | ... AA10: =AA9*(1-(s_margin+'02 Instellingen'!$D$22)) -> 324000
B11: Voorraad (DIO) | D11: ='02 Instellingen'!$D$25/s_dpm*D10 -> 455921.05 | E11: ='02 Instellingen'!$D$25/s_dpm*E10 -> 455921.05 | F11: ='02 Instellingen'!$D$25/s_dpm*F10 -> 553618.42 | G11: ='02 Instellingen'!$D$25/s_dpm*G10 -> 553618.42 | H11: ='02 Instellingen'!$D$25/s_dpm*H10 -> 586184.21 | I11: ='02 Instellingen'!$D$25/s_dpm*I10 -> 553618.42 | J11: ='02 Instellingen'!$D$25/s_dpm*J10 -> 455921.05 | K11: ='02 Instellingen'!$D$25/s_dpm*K10 -> 390789.47 | ... AA11: ='02 Instellingen'!$D$25/s_dpm*AA10 -> 586184.21
B12: Inkopen incl. BTW | D12: =(D10+D11-h_voorraad)*(1+v_btw) -> -50915.526 | E12: =(E10+E11-D11)*(1+v_btw) -> 304920 | F12: =(F10+F11-E11)*(1+v_btw) -> 488473.82 | G12: =(G10+G11-F11)*(1+v_btw) -> 370260 | H12: =(H10+H11-G11)*(1+v_btw) -> 431444.61 | I12: =(I10+I11-H11)*(1+v_btw) -> 330855.39 | J12: =(J10+J11-I11)*(1+v_btw) -> 186706.18 | K12: =(K10+K11-J11)*(1+v_btw) -> 182550.79 | L12: =(L10+L11-K11)*(1+v_btw) -> 628467.63 | ... AA12: =(AA10+AA11-Z11)*(1+v_btw) -> 273826.18
B13: Omzet incl. BTW | D13: =D9*(1+v_btw) -> 423500 | E13: =E9*(1+v_btw) -> 423500 | F13: =F9*(1+v_btw) -> 514250 | G13: =G9*(1+v_btw) -> 514250 | H13: =H9*(1+v_btw) -> 544500 | I13: =I9*(1+v_btw) -> 514250 | J13: =J9*(1+v_btw) -> 423500 | K13: =K9*(1+v_btw) -> 363000 | ... AA13: =AA9*(1+v_btw) -> 544500
B14: Debiteuren (DSO) | D14: ='02 Instellingen'!$D$23/s_dpm*D13 -> 626891.45 | E14: ='02 Instellingen'!$D$23/s_dpm*E13 -> 626891.45 | F14: ='02 Instellingen'!$D$23/s_dpm*F13 -> 761225.33 | G14: ='02 Instellingen'!$D$23/s_dpm*G13 -> 761225.33 | H14: ='02 Instellingen'!$D$23/s_dpm*H13 -> 806003.29 | I14: ='02 Instellingen'!$D$23/s_dpm*I13 -> 761225.33 | J14: ='02 Instellingen'!$D$23/s_dpm*J13 -> 626891.45 | K14: ='02 Instellingen'!$D$23/s_dpm*K13 -> 537335.53 | ... AA14: ='02 Instellingen'!$D$23/s_dpm*AA13 -> 806003.29
B15: Crediteuren (DPO) | D15: ='02 Instellingen'!$D$24/s_dpm*D12 -> -66994.114 | E15: ='02 Instellingen'!$D$24/s_dpm*E12 -> 401210.53 | F15: ='02 Instellingen'!$D$24/s_dpm*F12 -> 642728.7 | G15: ='02 Instellingen'!$D$24/s_dpm*G12 -> 487184.21 | H15: ='02 Instellingen'!$D$24/s_dpm*H12 -> 567690.27 | I15: ='02 Instellingen'!$D$24/s_dpm*I12 -> 435336.05 | J15: ='02 Instellingen'!$D$24/s_dpm*J12 -> 245666.03 | K15: ='02 Instellingen'!$D$24/s_dpm*K12 -> 240198.41 | ... AA15: ='02 Instellingen'!$D$24/s_dpm*AA12 -> 360297.61
B16: Ontvangsten klanten | D16: =h_debiteuren+D13-D14 -> 396608.55 | E16: =D14+E13-E14 -> 423500 | F16: =E14+F13-F14 -> 379916.12 | G16: =F14+G13-G14 -> 514250 | H16: =G14+H13-H14 -> 499722.04 | I16: =H14+I13-I14 -> 559027.96 | J16: =I14+J13-J14 -> 557833.88 | K16: =J14+K13-K14 -> 452555.92 | L16: =K14+L13-L14 -> 275832.24 | ... AA16: =Z14+AA13-AA14 -> 678833.88
B17: Betalingen leveranciers | D17: =h_crediteuren+D12-D15 -> 516078.59 | E17: =D15+E12-E15 -> -163284.64 | F17: =E15+F12-F15 -> 246955.64 | G17: =F15+G12-G15 -> 525804.49 | H17: =G15+H12-H15 -> 350938.55 | I17: =H15+I12-I15 -> 463209.62 | J17: =I15+J12-J15 -> 376376.2 | K17: =J15+K12-K15 -> 188018.41 | L17: =K15+L12-L15 -> 41734.945 | ... AA17: =Z15+AA12-AA15 -> 567192.53
B18: Overige kasstroom (uit actief model) | D18: ='12 Liquiditeitsprognose'!D30 -> -104000 | E18: ='12 Liquiditeitsprognose'!E30 -> -103950 | F18: ='12 Liquiditeitsprognose'!F30 -> -114150 | G18: ='12 Liquiditeitsprognose'!G30 -> -237668.63 | H18: ='12 Liquiditeitsprognose'!H30 -> -145200 | I18: ='12 Liquiditeitsprognose'!I30 -> -150000 | J18: ='12 Liquiditeitsprognose'!J30 -> -148766 | K18: ='12 Liquiditeitsprognose'!K30 -> -102150 | ... AA18: ='12 Liquiditeitsprognose'!AA30 -> -113850
B19: Netto kasstroom | D19: =D16-D17+D18 -> -223470.03 | E19: =E16-E17+E18 -> 482834.64 | F19: =F16-F17+F18 -> 18810.481 | G19: =G16-G17+G18 -> -249223.13 | H19: =H16-H17+H18 -> 3583.4938 | I19: =I16-I17+I18 -> -54181.659 | J19: =J16-J17+J18 -> 32691.684 | K19: =K16-K17+K18 -> 162387.51 | ... AA19: =AA16-AA17+AA18 -> -2208.6461
B20: EINDLIQUIDITEIT | D20: =s_bank0+D19 -> 76529.965 | E20: =D20+E19 -> 559364.61 | F20: =E20+F19 -> 578175.09 | G20: =F20+G19 -> 328951.96 | H20: =G20+H19 -> 332535.45 | I20: =H20+I19 -> 278353.8 | J20: =I20+J19 -> 311045.48 | K20: =J20+K19 -> 473432.99 | L20: =K20+L19 -> 512930.28 | ... AA20: =Z20+AA19 -> 233935.61
B22: SCENARIO: Best
B23: Omzet (excl. BTW) | D23: ='04 Input prognose'!D$8*s_omzet_jaar*(1+'02 Instellingen'!$E$21) -> 385000 | E23: ='04 Input prognose'!E$8*s_omzet_jaar*(1+'02 Instellingen'!$E$21) -> 385000 | F23: ='04 Input prognose'!F$8*s_omzet_jaar*(1+'02 Instellingen'!$E$21) -> 467500 | G23: ='04 Input prognose'!G$8*s_omzet_jaar*(1+'02 Instellingen'!$E$21) -> 467500 | H23: ='04 Input prognose'!H$8*s_omzet_jaar*(1+'02 Instellingen'!$E$21) -> 495000 | I23: ='04 Input prognose'!I$8*s_omzet_jaar*(1+'02 Instellingen'!$E$21) -> 467500 | J23: ='04 Input prognose'!J$8*s_omzet_jaar*(1+'02 Instellingen'!$E$21) -> 385000 | K23: ='04 Input prognose'!K$8*s_omzet_jaar*(1+'02 Instellingen'!$E$21) -> 330000 | ... AA23: ='04 Input prognose'!AA$8*s_omzet_jaar*(1+'02 Instellingen'!$E$21) -> 495000
B24: Inkoopwaarde omzet | D24: =D23*(1-(s_margin+'02 Instellingen'!$E$22)) -> 269500 | E24: =E23*(1-(s_margin+'02 Instellingen'!$E$22)) -> 269500 | F24: =F23*(1-(s_margin+'02 Instellingen'!$E$22)) -> 327250 | G24: =G23*(1-(s_margin+'02 Instellingen'!$E$22)) -> 327250 | H24: =H23*(1-(s_margin+'02 Instellingen'!$E$22)) -> 346500 | I24: =I23*(1-(s_margin+'02 Instellingen'!$E$22)) -> 327250 | J24: =J23*(1-(s_margin+'02 Instellingen'!$E$22)) -> 269500 | K24: =K23*(1-(s_margin+'02 Instellingen'!$E$22)) -> 231000 | ... AA24: =AA23*(1-(s_margin+'02 Instellingen'!$E$22)) -> 346500
B25: Voorraad (DIO) | D25: ='02 Instellingen'!$E$25/s_dpm*D24 -> 398930.92 | E25: ='02 Instellingen'!$E$25/s_dpm*E24 -> 398930.92 | F25: ='02 Instellingen'!$E$25/s_dpm*F24 -> 484416.12 | G25: ='02 Instellingen'!$E$25/s_dpm*G24 -> 484416.12 | H25: ='02 Instellingen'!$E$25/s_dpm*H24 -> 512911.18 | I25: ='02 Instellingen'!$E$25/s_dpm*I24 -> 484416.12 | J25: ='02 Instellingen'!$E$25/s_dpm*J24 -> 398930.92 | K25: ='02 Instellingen'!$E$25/s_dpm*K24 -> 341940.79 | ... AA25: ='02 Instellingen'!$E$25/s_dpm*AA24 -> 512911.18
B26: Inkopen incl. BTW | D26: =(D24+D25-h_voorraad)*(1+v_btw) -> -98698.586 | E26: =(E24+E25-D25)*(1+v_btw) -> 326095 | F26: =(F24+F25-E25)*(1+v_btw) -> 499409.59 | G26: =(G24+G25-F25)*(1+v_btw) -> 395972.5 | H26: =(H24+H25-G25)*(1+v_btw) -> 453744.03 | I26: =(I24+I25-H25)*(1+v_btw) -> 361493.47 | J26: =(J24+J25-I25)*(1+v_btw) -> 222657.91 | K26: =(K24+K25-J25)*(1+v_btw) -> 210551.94 | L26: =(L24+L25-K25)*(1+v_btw) -> 626139.18 | ... AA26: =(AA24+AA25-Z25)*(1+v_btw) -> 315827.91
B27: Omzet incl. BTW | D27: =D23*(1+v_btw) -> 465850 | E27: =E23*(1+v_btw) -> 465850 | F27: =F23*(1+v_btw) -> 565675 | G27: =G23*(1+v_btw) -> 565675 | H27: =H23*(1+v_btw) -> 598950 | I27: =I23*(1+v_btw) -> 565675 | J27: =J23*(1+v_btw) -> 465850 | K27: =K23*(1+v_btw) -> 399300 | ... AA27: =AA23*(1+v_btw) -> 598950
B28: Debiteuren (DSO) | D28: ='02 Instellingen'!$E$23/s_dpm*D27 -> 582312.5 | E28: ='02 Instellingen'!$E$23/s_dpm*E27 -> 582312.5 | F28: ='02 Instellingen'!$E$23/s_dpm*F27 -> 707093.75 | G28: ='02 Instellingen'!$E$23/s_dpm*G27 -> 707093.75 | H28: ='02 Instellingen'!$E$23/s_dpm*H27 -> 748687.5 | I28: ='02 Instellingen'!$E$23/s_dpm*I27 -> 707093.75 | J28: ='02 Instellingen'!$E$23/s_dpm*J27 -> 582312.5 | K28: ='02 Instellingen'!$E$23/s_dpm*K27 -> 499125 | ... AA28: ='02 Instellingen'!$E$23/s_dpm*AA27 -> 748687.5
B29: Crediteuren (DPO) | D29: ='02 Instellingen'!$E$24/s_dpm*D26 -> -146099.88 | E29: ='02 Instellingen'!$E$24/s_dpm*E26 -> 482706.41 | F29: ='02 Instellingen'!$E$24/s_dpm*F26 -> 739257.62 | G29: ='02 Instellingen'!$E$24/s_dpm*G26 -> 586143.5 | H29: ='02 Instellingen'!$E$24/s_dpm*H26 -> 671660.57 | I29: ='02 Instellingen'!$E$24/s_dpm*I26 -> 535105.47 | J29: ='02 Instellingen'!$E$24/s_dpm*J26 -> 329592.3 | K29: ='02 Instellingen'!$E$24/s_dpm*K26 -> 311672.28 | ... AA29: ='02 Instellingen'!$E$24/s_dpm*AA26 -> 467508.42
B30: Ontvangsten klanten | D30: =h_debiteuren+D27-D28 -> 483537.5 | E30: =D28+E27-E28 -> 465850 | F30: =E28+F27-F28 -> 440893.75 | G30: =F28+G27-G28 -> 565675 | H30: =G28+H27-H28 -> 557356.25 | I30: =H28+I27-I28 -> 607268.75 | J30: =I28+J27-J28 -> 590631.25 | K30: =J28+K27-K28 -> 482487.5 | L30: =K28+L27-L28 -> 349387.5 | ... AA30: =Z28+AA27-AA28 -> 723731.25
B31: Betalingen leveranciers | D31: =h_crediteuren+D26-D29 -> 547401.29 | E31: =D29+E26-E29 -> -302711.29 | F31: =E29+F26-F29 -> 242858.39 | G31: =F29+G26-G29 -> 549086.61 | H31: =G29+H26-H29 -> 368226.96 | I31: =H29+I26-I29 -> 498048.57 | J31: =I29+J26-J29 -> 428171.07 | K31: =J29+K26-K29 -> 228471.96 | L31: =K29+L26-L29 -> 10960.702 | ... AA31: =Z29+AA26-AA29 -> 623417.15
B32: Overige kasstroom (uit actief model) | D32: ='12 Liquiditeitsprognose'!D30 -> -104000 | E32: ='12 Liquiditeitsprognose'!E30 -> -103950 | F32: ='12 Liquiditeitsprognose'!F30 -> -114150 | G32: ='12 Liquiditeitsprognose'!G30 -> -237668.63 | H32: ='12 Liquiditeitsprognose'!H30 -> -145200 | I32: ='12 Liquiditeitsprognose'!I30 -> -150000 | J32: ='12 Liquiditeitsprognose'!J30 -> -148766 | K32: ='12 Liquiditeitsprognose'!K30 -> -102150 | ... AA32: ='12 Liquiditeitsprognose'!AA30 -> -113850
B33: Netto kasstroom | D33: =D30-D31+D32 -> -167863.79 | E33: =E30-E31+E32 -> 664611.29 | F33: =F30-F31+F32 -> 83885.362 | G33: =G30-G31+G32 -> -221080.24 | H33: =H30-H31+H32 -> 43929.287 | I33: =I30-I31+I32 -> -40779.824 | J33: =J30-J31+J32 -> 13694.176 | K33: =K30-K31+K32 -> 151865.54 | ... AA33: =AA30-AA31+AA32 -> -13535.899
B34: EINDLIQUIDITEIT | D34: =s_bank0+D33 -> 132136.21 | E34: =D34+E33 -> 796747.5 | F34: =E34+F33 -> 880632.86 | G34: =F34+G33 -> 659552.62 | H34: =G34+H33 -> 703481.91 | I34: =H34+I33 -> 662702.08 | J34: =I34+J33 -> 676396.26 | K34: =J34+K33 -> 828261.79 | L34: =K34+L33 -> 972088.59 | ... AA34: =Z34+AA33 -> 1092122.6
B36: SCENARIO: Worst
B37: Omzet (excl. BTW) | D37: ='04 Input prognose'!D$8*s_omzet_jaar*(1+'02 Instellingen'!$F$21) -> 315000 | E37: ='04 Input prognose'!E$8*s_omzet_jaar*(1+'02 Instellingen'!$F$21) -> 315000 | F37: ='04 Input prognose'!F$8*s_omzet_jaar*(1+'02 Instellingen'!$F$21) -> 382500 | G37: ='04 Input prognose'!G$8*s_omzet_jaar*(1+'02 Instellingen'!$F$21) -> 382500 | H37: ='04 Input prognose'!H$8*s_omzet_jaar*(1+'02 Instellingen'!$F$21) -> 405000 | I37: ='04 Input prognose'!I$8*s_omzet_jaar*(1+'02 Instellingen'!$F$21) -> 382500 | J37: ='04 Input prognose'!J$8*s_omzet_jaar*(1+'02 Instellingen'!$F$21) -> 315000 | K37: ='04 Input prognose'!K$8*s_omzet_jaar*(1+'02 Instellingen'!$F$21) -> 270000 | ... AA37: ='04 Input prognose'!AA$8*s_omzet_jaar*(1+'02 Instellingen'!$F$21) -> 405000
B38: Inkoopwaarde omzet | D38: =D37*(1-(s_margin+'02 Instellingen'!$F$22)) -> 236250 | E38: =E37*(1-(s_margin+'02 Instellingen'!$F$22)) -> 236250 | F38: =F37*(1-(s_margin+'02 Instellingen'!$F$22)) -> 286875 | G38: =G37*(1-(s_margin+'02 Instellingen'!$F$22)) -> 286875 | H38: =H37*(1-(s_margin+'02 Instellingen'!$F$22)) -> 303750 | I38: =I37*(1-(s_margin+'02 Instellingen'!$F$22)) -> 286875 | J38: =J37*(1-(s_margin+'02 Instellingen'!$F$22)) -> 236250 | K38: =K37*(1-(s_margin+'02 Instellingen'!$F$22)) -> 202500 | ... AA38: =AA37*(1-(s_margin+'02 Instellingen'!$F$22)) -> 303750
B39: Voorraad (DIO) | D39: ='02 Instellingen'!$F$25/s_dpm*D38 -> 582853.62 | E39: ='02 Instellingen'!$F$25/s_dpm*E38 -> 582853.62 | F39: ='02 Instellingen'!$F$25/s_dpm*F38 -> 707750.82 | G39: ='02 Instellingen'!$F$25/s_dpm*G38 -> 707750.82 | H39: ='02 Instellingen'!$F$25/s_dpm*H38 -> 749383.22 | I39: ='02 Instellingen'!$F$25/s_dpm*I38 -> 707750.82 | J39: ='02 Instellingen'!$F$25/s_dpm*J38 -> 582853.62 | K39: ='02 Instellingen'!$F$25/s_dpm*K38 -> 499588.82 | ... AA39: ='02 Instellingen'!$F$25/s_dpm*AA38 -> 749383.22
B40: Inkopen incl. BTW | D40: =(D38+D39-h_voorraad)*(1+v_btw) -> 83615.378 | E40: =(E38+E39-D39)*(1+v_btw) -> 285862.5 | F40: =(F38+F39-E39)*(1+v_btw) -> 498244.37 | G40: =(G38+G39-F39)*(1+v_btw) -> 347118.75 | H40: =(H38+H39-G39)*(1+v_btw) -> 417912.71 | I40: =(I38+I39-H39)*(1+v_btw) -> 296743.54 | J40: =(J38+J39-I39)*(1+v_btw) -> 134736.88 | K40: =(K38+K39-J39)*(1+v_btw) -> 144274.59 | L40: =(L38+L39-K39)*(1+v_btw) -> 669788.73 | ... AA40: =(AA38+AA39-Z39)*(1+v_btw) -> 216411.88
B41: Omzet incl. BTW | D41: =D37*(1+v_btw) -> 381150 | E41: =E37*(1+v_btw) -> 381150 | F41: =F37*(1+v_btw) -> 462825 | G41: =G37*(1+v_btw) -> 462825 | H41: =H37*(1+v_btw) -> 490050 | I41: =I37*(1+v_btw) -> 462825 | J41: =J37*(1+v_btw) -> 381150 | K41: =K37*(1+v_btw) -> 326700 | ... AA41: =AA37*(1+v_btw) -> 490050
B42: Debiteuren (DSO) | D42: ='02 Instellingen'!$F$23/s_dpm*D41 -> 752269.74 | E42: ='02 Instellingen'!$F$23/s_dpm*E41 -> 752269.74 | F42: ='02 Instellingen'!$F$23/s_dpm*F41 -> 913470.39 | G42: ='02 Instellingen'!$F$23/s_dpm*G41 -> 913470.39 | H42: ='02 Instellingen'!$F$23/s_dpm*H41 -> 967203.95 | I42: ='02 Instellingen'!$F$23/s_dpm*I41 -> 913470.39 | J42: ='02 Instellingen'!$F$23/s_dpm*J41 -> 752269.74 | K42: ='02 Instellingen'!$F$23/s_dpm*K41 -> 644802.63 | ... AA42: ='02 Instellingen'!$F$23/s_dpm*AA41 -> 967203.95
B43: Crediteuren (DPO) | D43: ='02 Instellingen'!$F$24/s_dpm*D40 -> 82515.176 | E43: ='02 Instellingen'!$F$24/s_dpm*E40 -> 282101.15 | F43: ='02 Instellingen'!$F$24/s_dpm*F40 -> 491688.52 | G43: ='02 Instellingen'!$F$24/s_dpm*G40 -> 342551.4 | H43: ='02 Instellingen'!$F$24/s_dpm*H40 -> 412413.85 | I43: ='02 Instellingen'!$F$24/s_dpm*I40 -> 292839.02 | J43: ='02 Instellingen'!$F$24/s_dpm*J40 -> 132964.03 | K43: ='02 Instellingen'!$F$24/s_dpm*K40 -> 142376.24 | ... AA43: ='02 Instellingen'!$F$24/s_dpm*AA40 -> 213564.36
B44: Ontvangsten klanten | D44: =h_debiteuren+D41-D42 -> 228880.26 | E44: =D42+E41-E42 -> 381150 | F44: =E42+F41-F42 -> 301624.34 | G44: =F42+G41-G42 -> 462825 | H44: =G42+H41-H42 -> 436316.45 | I44: =H42+I41-I42 -> 516558.55 | J44: =I42+J41-J42 -> 542350.66 | K44: =J42+K41-K42 -> 434167.11 | L44: =K42+L41-L42 -> 167648.68 | ... AA44: =Z42+AA41-AA42 -> 651250.66
B45: Betalingen leveranciers | D45: =h_crediteuren+D40-D43 -> 501100.2 | E45: =D43+E40-E43 -> 86276.525 | F45: =E43+F40-F43 -> 288657 | G45: =F43+G40-G43 -> 496255.87 | H45: =G43+H40-H43 -> 348050.25 | I45: =H43+I40-I43 -> 416318.37 | J45: =I43+J40-J43 -> 294611.88 | K45: =J43+K40-K43 -> 134862.38 | L45: =K43+L40-L43 -> 151189.25 | ... AA45: =Z43+AA40-AA43 -> 475711.63
B46: Overige kasstroom (uit actief model) | D46: ='12 Liquiditeitsprognose'!D30 -> -104000 | E46: ='12 Liquiditeitsprognose'!E30 -> -103950 | F46: ='12 Liquiditeitsprognose'!F30 -> -114150 | G46: ='12 Liquiditeitsprognose'!G30 -> -237668.63 | H46: ='12 Liquiditeitsprognose'!H30 -> -145200 | I46: ='12 Liquiditeitsprognose'!I30 -> -150000 | J46: ='12 Liquiditeitsprognose'!J30 -> -148766 | K46: ='12 Liquiditeitsprognose'!K30 -> -102150 | ... AA46: ='12 Liquiditeitsprognose'!AA30 -> -113850
B47: Netto kasstroom | D47: =D44-D45+D46 -> -376219.94 | E47: =E44-E45+E46 -> 190923.48 | F47: =F44-F45+F46 -> -101182.66 | G47: =G44-G45+G46 -> -271099.5 | H47: =H44-H45+H46 -> -56933.802 | I47: =I44-I45+I46 -> -49759.822 | J47: =J44-J45+J46 -> 98972.78 | K47: =K44-K45+K46 -> 197154.73 | ... AA47: =AA44-AA45+AA46 -> 61689.032
B48: EINDLIQUIDITEIT | D48: =s_bank0+D47 -> -76219.939 | E48: =D48+E47 -> 114703.54 | F48: =E48+F47 -> 13520.88 | G48: =F48+G47 -> -257578.62 | H48: =G48+H47 -> -314512.43 | I48: =H48+I47 -> -364272.25 | J48: =I48+J47 -> -265299.47 | K48: =J48+K47 -> -68144.741 | L48: =K48+L47 -> -246285.31 | ... AA48: =Z48+AA47 -> -936969.11
B51: VERGELIJKING SCENARIO'S
B52: KPI | C52: Base | D52: Best | E52: Worst
B53: Minimale liquiditeit | C53: =MIN(D20:AA20) -> 76529.965 | D53: =MIN(D34:AA34) -> 132136.21 | E53: =MIN(D48:AA48) -> -998658.14
B54: Max. financieringsbehoefte | C54: =MAX(0,s_buffer-MIN(D20:AA20)) -> 23470.035 | D54: =MAX(0,s_buffer-MIN(D34:AA34)) -> 0 | E54: =MAX(0,s_buffer-MIN(D48:AA48)) -> 1098658.1
B55: Eindliquiditeit (maand 24) | C55: =AA20 -> 233935.61 | D55: =AA34 -> 1092122.6 | E55: =AA48 -> -936969.11

Sheet 14 Import
B2: IMPORT - EXACT ONLINE / EXCEL / CSV
B3: 14 Import · Plak hier een grootboekexport · mappingtabel brengt data naar modelcategorieën
B5: EXACT ONLINE IMPORT-TEMPLATE (plak export vanaf rij 8)
B7: Datum | C7: Grootboekrekening | D7: Omschrijving | E7: Bedrag | F7: Debet/Credit | G7: Categorie | H7: Periode
B8: 2026-01-05 | C8: 8000 Omzet handel | D8: Verkoop klant A | E8: 125000 | F8: C | G8: Omzet | H8: 2026-01
B9: 2026-01-08 | C9: 7000 Inkoopwaarde | D9: Inkoop leverancier X | E9: -82000 | F9: D | G9: Inkoop | H9: 2026-01
B10: 2026-01-25 | C10: 4000 Lonen | D10: Salarissen januari | E10: -52000 | F10: D | G10: Personeel | H10: 2026-01
B13: MAPPINGTABEL (koppel grootboek/categorie -> modelcategorie -> kasstroom)
B14: Bronrekening / categorie | C14: Modelcategorie | D14: Cashflowcategorie
B15: 8000 Omzet handel | C15: Omzet | D15: Ontvangsten klanten
B16: 7000 Inkoopwaarde | C16: Inkoop | D16: Betalingen leveranciers
B17: 4000 Lonen | C17: Personeel | D17: Personeel
B18: 4300 Huisvesting | C18: Huisvesting | D18: Overige kosten
B19: 4400 Transport | C19: Transport | D19: Overige kosten
B20: 4800 Overige kosten | C20: Overige kosten | D20: Overige kosten
B21: 1300 Debiteuren | C21: Debiteuren | D21: Werkkapitaal
B22: 3000 Voorraad | C22: Voorraad | D22: Werkkapitaal
B23: 1600 Crediteuren | C23: Crediteuren | D23: Werkkapitaal
B24: 1520 BTW | C24: Belastingen | D24: BTW
B25: 0700 Materiële vaste activa | C25: Investeringen | D25: Investeringen
B26: 0800 Leningen o/g | C26: Financiering | D26: Financiering
B29: Power Query-route (aanbevolen voor herhaalde import):
B30: 1. Data > Gegevens ophalen > Uit bestand (CSV/Excel-export uit Exact Online).
B31: 2. Koppel de query aan deze mappingtabel (Samenvoegen op Bronrekening).
B32: 3. Groepeer per Modelcategorie en Periode; laad naar het model.
B33: 4. Vernieuwen (Ctrl+Alt+F5) actualiseert historie en startposities.

Sheet 15 Controle
B2: CONTROLEBLAD - MODELINTEGRITEIT
B3: 15 Controle · Automatische controles · status MODEL OK / ACTIE VEREIST
B5: CONTROLES
B6: # | C6: Controle | D6: Uitkomst | E6: Norm | F6: Status
B7: 1 | C7: Seizoensgewicht jaar 1 = 100% | D7: ='04 Input prognose'!$D$13 -> 1 | E7: =100% -> 1 | F7: =IF(ROUND(D7,4)=1,"OK","FOUT") -> OK
B8: 2 | C8: Seizoensgewicht jaar 2 = 100% | D8: ='04 Input prognose'!$D$14 -> 1 | E8: =100% -> 1 | F8: =IF(ROUND(D8,4)=1,"OK","FOUT") -> OK
B9: 3 | C9: Begin + netto = eind (maand 12) | D9: ='12 Liquiditeitsprognose'!P8+'12 Liquiditeitsprognose'!P24-'12 Liquiditeitsprognose'!P25 -> 0 | E9: =0 -> 0 | F9: =IF(ROUND(D9,0)=0,"OK","FOUT") -> OK
B10: 4 | C10: Geen negatieve voorraad | D10: =MIN('06 Werkkapitaal'!$D$10:$AA$10) -> 390789.47 | E10: >= 0 | F10: =IF(D10>=0,"OK","LET OP") -> OK
B11: 5 | C11: Leningstand niet negatief | D11: =MIN('10 Financiering'!$D$13:$AA$13) -> 660000 | E11: >= 0 | F11: =IF(D11>=0,"OK","FOUT") -> OK
B12: 6 | C12: Openingssaldo bank ingevuld | D12: =s_bank0 -> 300000 | E12: > 0 | F12: =IF(D12>0,"OK","LET OP") -> OK
B13: 7 | C13: Startdatum ingevuld | D13: =IF(s_start>0,1,0) -> 1 | E13: ingevuld | F13: =IF(D13=1,"OK","FOUT") -> OK
B14: 8 | C14: Actief scenario geldig | D14: =IF(OR(s_scenario="Base",s_scenario="Best",s_scenario="Worst",s_scenario="Custom"),1,0) -> 1 | E14: geldig | F14: =IF(D14=1,"OK","FOUT") -> OK
B15: 9 | C15: Buffer > 0 | D15: =s_buffer -> 100000 | E15: > 0 | F15: =IF(D15>0,"OK","LET OP") -> OK
B16: 10 | C16: Alle scenario's rekenen door (min eind) | D16: =MIN('13 Scenarioanalyse'!$D$48:$AA$48) -> -998658.14 | E16: getal | F16: =IF(ISNUMBER(D16),"OK","FOUT") -> OK
B18: =IF(COUNTIF(F7:F16,"FOUT")>0,"⛔ ACTIE VEREIST - zie FOUT-regels",IF(COUNTIF(F7:F16,"LET OP")>0,"⚠ LET OP - controleer aandachtspunten","✅ MODEL OK - alle controles geslaagd")) -> ✅ MODEL OK - alle controles geslaagd

Sheet 16 Toelichting
B2: TOELICHTING VOOR GEBRUIKER & ACCOUNTANT
B3: 16 Toelichting · Werking, aannames, methodiek en leeswijzer
C6: KLEURCODERING
C7: • Geel = invoercel (handmatig). • Blauw getal = invoer. • Groen getal = link naar ander tabblad. • Zwart = berekening. • Donkergroen = belangrijke output.
C9: LAAGSTRUCTUUR (geen black box)
C10: INPUT (02 Instellingen, 03 Historie, 04 Input, 07-11 aannames) -> BEREKENING (05 Omzet, 06 Werkkapitaal, 12 Liquiditeit) -> OUTPUT (01 Dashboard, 13 Scenario).
C11: Elke prognose is herleidbaar: elk bedrag verwijst via zichtbare formules naar een invoercel of aanname. Er is geen verborgen logica of VBA.
C13: METHODIEK WERKKAPITAAL (kern)
C14: Voorraad, debiteuren en crediteuren worden gemodelleerd als STREEFSALDI op basis van dagen (DSO/DPO/DIO):
C15: Voorraad(maand) = DIO / 30,4 × inkoopwaarde omzet van die maand
C16: Debiteuren(maand) = DSO / 30,4 × omzet incl. BTW van die maand
C17: Crediteuren(maand)= DPO / 30,4 × inkopen incl. BTW van die maand
C18: Ontvangsten = beginstand debiteuren + facturatie − eindstand debiteuren. Betalingen leveranciers analoog. Zo vertaalt een langere DSO zich direct in een lagere kasontvangst en hogere financieringsbehoefte.
C19: Inkopen = inkoopwaarde omzet + toename voorraad (voorraadopbouw kost dus extra cash).
... C35: Prognosemodel op basis van aannames; werkelijke uitkomsten wijken af. Bedoeld als adviesinstrument voor het klantgesprek, niet als jaarrekening of fiscale aangifte.

Sheet 17 Copilot Prompts
B2: COPILOT IN EXCEL - KANT-EN-KLARE PROMPTS
B3: 17 Copilot Prompts · Kopieer een prompt naar Copilot voor directe analyse van het model
C5: PROMPTS
C6: 1 | D6: Analyseer de liquiditeitsprognose en benoem de drie belangrijkste oorzaken van de verwachte financieringsbehoefte.
C7: 2 | D7: Welke maanden hebben een eindliquiditeit onder de minimale buffer? Zet ze op een rij met het tekort.
C8: 3 | D8: Wat gebeurt er met de liquiditeit als de debiteurentermijn (DSO) met 15 dagen toeneemt?
C9: 4 | D9: Analyseer de ontwikkeling van brutomarge en omzet over de 24 maanden.
C10: 5 | D10: Welke kostencategorieën groeien sneller dan de omzet?
C11: 6 | D11: Welke maatregelen hebben waarschijnlijk de grootste positieve invloed op de liquiditeit?
C12: 7 | D12: Vergelijk Base Case met Worst Case en beschrijf het verschil in minimale liquiditeit.
C13: 8 | D13: Bereken hoeveel extra liquiditeit nodig is bij een daling van de omzet met 10%.
C14: 9 | D14: Hoeveel cash zit er vast in werkkapitaal (voorraad + debiteuren − crediteuren) per maand?
C15: 10 | D15: Maak een managementsamenvatting van de liquiditeitsprognose in vijf bullets.
C16: 11 | D16: Wat is het effect op de eindliquiditeit als de voorraad met € 250.000 toeneemt?
C17: 12 | D17: Bereken de Cash Conversion Cycle per maand en beschrijf de trend.
