Workbook
Name Klant_Naam: START!$C$6
Name Peildatum_Actueel: START!$C$8
Name Heeft_Partner: START!$C$9
Name Partner_Naam: START!$C$10
Name Categorieen: '90_Config'!$B$7:$B$14
Name TypeLijst: '90_Config'!$C$7:$C$8
Name BoxLijst: '90_Config'!$D$7:$D$10
Name EigenaarLijst: '90_Config'!$E$7:$E$9
Name BronLijst: '90_Config'!$F$7:$F$10
Name JaNee: '90_Config'!$G$7:$G$8
Name Betrouwbaar: '90_Config'!$H$7:$H$8
Name IB_Box3_Grondslag: '02_Input_IB'!$E$19
Name IB_AB_Waarde: '02_Input_IB'!$E$13
Name JR_EigenVermogen: '03_Input_JR'!$C$14
Name JR_RC_DGA: '03_Input_JR'!$C$17
Name JR_ODV: '03_Input_JR'!$C$15
Name v_Peildatum: '04_Input_Vermogen'!$B$6:$B$405
Name v_Categorie: '04_Input_Vermogen'!$C$6:$C$405
Name v_Type: '04_Input_Vermogen'!$F$6:$F$405
Name v_Box: '04_Input_Vermogen'!$G$6:$G$405
Name v_Eigenaar: '04_Input_Vermogen'!$H$6:$H$405
Name v_Aandeel: '04_Input_Vermogen'!$I$6:$I$405
Name v_Waarde: '04_Input_Vermogen'!$J$6:$J$405
Name v_Teken: '04_Input_Vermogen'!$K$6:$K$405
Name h_Peildatum: '05_Historie'!$B$6:$B$8
Name h_Netto: '05_Historie'!$E$6:$E$8
Name calc_CatLabels: '11_Berekeningen'!$B$13:$B$18
Name calc_CatValues: '11_Berekeningen'!$C$13:$C$18
Name calc_Netto: '11_Berekeningen'!$C$8
Name calc_NettoKlant: '11_Berekeningen'!$D$8
Name calc_NettoPartner: '11_Berekeningen'!$E$8
Name calc_Bezit: '11_Berekeningen'!$C$6
Name calc_Schuld: '11_Berekeningen'!$C$7
Name calc_Box3Monitor: '11_Berekeningen'!$C$25

Sheet START
B2: VERMOGENSMONITOR
B3: Geïntegreerd standaardbestand · vermogensinzicht & financiële planning
B5: KLANTGEGEVENS
B6: Klantnaam | C6: Voorbeeld: J. Jansen (fictief)
B7: Dossier / relatienummer | C7: REL-0001
B8: Peildatum (actueel) | C8: 46023
B9: Heeft partner? (JA/NEE) | C9: JA
B10: Naam partner | C10: Voorbeeld: M. Jansen (fictief)
B11: Opgesteld door | C11: Newtone
B12: Versie template | C12: v1.0 (MVP)
B14: NAVIGATIE
B15: ▶ 01_Klant | C15: Klant- en partnergegevens
B16: ▶ 02_Input_IB | C16: Overname aangifte inkomstenbelasting (box 1/2/3)
B17: ▶ 03_Input_JR | C17: Overname jaarrekening (balans + W&V)
B18: ▶ 04_Input_Vermogen | C18: Bezittingen & schulden (feitentabel)
B19: ▶ 05_Historie | C19: Meerjarige snapshots (trend)
B20: ▶ 11_Berekeningen | C20: KPI's, ratio's, consolidatie
B21: ▶ 20_Dashboard | C21: Cliëntdashboard
B22: ▶ 21_Scenario | C22: Financiële planning / scenario's
B23: ▶ 99_Controles | C23: Kwaliteitscontroles & aansluitingen
B25: STATUS (zie 99_Controles)
B26: Volledigheid invoer | C26: ='99_Controles'!$C$6
B27: Aansluiting IB ↔ Monitor | C27: ='99_Controles'!$C$7

Sheet 01_Klant
B2: KLANT- EN PARTNERGEGEVENS
B3: 01_Klant · Blauwe cellen = handmatige invoer · partnerkolom volgt uit Heeft_Partner
B5: Gegeven | C5: Klant | D5: =IF(Heeft_Partner="JA","Partner","(geen partner)")
B6: Naam | C6: =Klant_Naam | D6: =IF(Heeft_Partner="JA",Partner_Naam,"-")
B7: Geboortedatum | C7: 27526 | D7: 28736
B8: BSN (gemaskeerd)
B9: Burgerlijke staat
B10: Fiscaal partnerschap (JA/NEE) | C10: JA | D10: JA
B11: AOW-leeftijd (indicatief)
B12: E-mail

Sheet 02_Input_IB
B2: OVERNAME AANGIFTE INKOMSTENBELASTING
B3: 02_Input_IB · Box 1/2/3 · verdeling tussen fiscale partners · voedt controles & box 3-grondslag
B5: Post (aangifte IB) | C5: Klant | D5: Partner | E5: Totaal | F5: Toelichting
B6: BOX 1 – werk en woning
B7: Inkomen uit werk (loon/winst) | C7: 85000 | D7: 42000 | E7: =C7+D7
B8: Eigenwoningforfait | C8: 5200 | D8: 0 | E8: =C8+D8
B9: Aftrekbare hypotheekrente | C9: -9600 | D9: 0 | E9: =C9+D9
B10: Belastbaar inkomen box 1 | C10: =SUM(C7:C9) | D10: =SUM(D7:D9) | E10: =C10+D10
B11: BOX 2 – aanmerkelijk belang
B12: Reguliere voordelen (dividend) | C12: 0 | D12: 0 | E12: =C12+D12
B13: Waarde aandelen (economisch) | C13: 300000 | D13: 0 | E13: =C13+D13
B14: BOX 3 – sparen en beleggen
B15: Bank- en spaartegoeden | C15: 52500 | D15: 52500 | E15: =C15+D15
B16: Beleggingen | C16: 120000 | D16: 0 | E16: =C16+D16
B17: Overige bezittingen box 3 | C17: 0 | D17: 0 | E17: =C17+D17
B18: Schulden box 3 | C18: -5000 | D18: -5000 | E18: =C18+D18
B19: Grondslag box 3 (voor vrijstelling) | C19: =SUM(C15:C18) | D19: =SUM(D15:D18) | E19: =C19+D19

Sheet 03_Input_JR
B2: OVERNAME JAARREKENING (BV / DGA)
B3: 03_Input_JR · Balans + W&V · brug privé↔zakelijk: eigen vermogen, r/c DGA, ODV, dividendruimte
B5: Post jaarrekening | C5: Bedrag | D5: Toelichting
B6: BALANS – ACTIVA
B7: Materiële vaste activa | C7: 45000
B8: Financiële vaste activa | C8: 20000
B9: Voorraden | C9: 0
B10: Debiteuren | C10: 60000
B11: Liquide middelen | C11: 300000
B12: Balanstotaal (activa) | C12: =SUM(C7:C11)
B13: BALANS – PASSIVA
B14: Eigen vermogen | C14: 305000 | D14: → basis AB-waarde box 2
B15: Voorzieningen / ODV | C15: 40000 | D15: oudedagsverplichting
B16: Langlopende schulden | C16: 0
B17: Rekening-courant DGA | C17: 50000 | D17: → schuld/vordering privé
B18: Kortlopende schulden | C18: 30000
B19: Balanstotaal (passiva) | C19: =SUM(C14:C18)
B20: WINST- EN VERLIESREKENING
B21: Omzet | C21: 420000
B22: Bedrijfskosten | C22: -300000
B23: Resultaat voor belasting | C23: =SUM(C21:C22)
B24: Uitkeerbare reserve (dividendruimte) | C24: 150000 | D24: [AANNAME] indicatief

Sheet 04_Input_Vermogen
B2: BEZITTINGEN & SCHULDEN — genormaliseerde feitentabel
B3: 04_Input_Vermogen · Eén regel per component · eigenaar stuurt partnerlogica · dit voedt alle berekeningen
B4: LEGENDA: vul de blauwe kolommen in (Peildatum t/m Waarde, Bron). 'Teken' rekent automatisch. Eigenaar=Gezamenlijk → Aandeel klant % bepaalt de splitsing (default 50%).
B5: Peildatum | C5: Categorie | D5: Subcategorie | E5: Omschrijving | F5: Type | G5: Box | H5: Eigenaar | I5: Aandeel klant % | J5: Waarde | K5: Teken | L5: Bron | M5: Betrouwbaarheid | N5: Toelichting
B6: 46023 | C6: Liquiditeiten | D6: Betaalrekening | E6: Gezamenlijke betaalrekening | F6: Bezitting | G6: Box 3 | H6: Gezamenlijk | I6: 0.5 | J6: 25000 | K6: =IF($F6="Schuld",-1,IF($F6="",0,1)) | L6: Bank
B7: 46023 | C7: Liquiditeiten | D7: Spaarrekening | E7: Spaargeld | F7: Bezitting | G7: Box 3 | H7: Gezamenlijk | I7: 0.5 | J7: 80000 | K7: =IF($F7="Schuld",-1,IF($F7="",0,1)) | L7: Bank
B8: 46023 | C8: Vastgoed | D8: Eigen woning | E8: Woning (WOZ/marktwaarde) | F8: Bezitting | G8: Box 1 | H8: Gezamenlijk | I8: 0.5 | J8: 550000 | K8: =IF($F8="Schuld",-1,IF($F8="",0,1)) | L8: Handmatig
B9: 46023 | C9: Beleggingen | D9: Effectenportefeuille | E9: Beleggingsrekening | F9: Bezitting | G9: Box 3 | H9: Klant | I9: 1 | J9: 120000 | K9: =IF($F9="Schuld",-1,IF($F9="",0,1)) | L9: Aangifte IB
B10: 46023 | C10: Pensioen/ODV | D10: Lijfrente | E10: Lijfrentepolis | F10: Bezitting | G10: Box 1 | H10: Klant | I10: 1 | J10: 45000 | K10: =IF($F10="Schuld",-1,IF($F10="",0,1)) | L10: Handmatig
B11: 46023 | C11: Onderneming/AB | D11: Aandelen Holding BV | E11: Aanmerkelijk belang (EV) | F11: Bezitting | G11: Box 2 | H11: Klant | I11: 1 | J11: 305000 | K11: =IF($F11="Schuld",-1,IF($F11="",0,1)) | L11: Jaarrekening
B12: 46023 | C12: Overige bezitting | D12: Voertuig | E12: Auto | F12: Bezitting | G12: n.v.t. | H12: Gezamenlijk | I12: 0.5 | J12: 30000 | K12: =IF($F12="Schuld",-1,IF($F12="",0,1)) | L12: Handmatig
B13: 46023 | C13: Hypotheek | D13: Eigenwoningschuld | E13: Hypotheek eigen woning | F13: Schuld | G13: Box 1 | H13: Gezamenlijk | I13: 0.5 | J13: 320000 | K13: =IF($F13="Schuld",-1,IF($F13="",0,1)) | L13: Handmatig
B14: 46023 | C14: Overige schuld | D14: Rekening-courant DGA | E14: R/C schuld aan BV | F14: Schuld | G14: Box 2 | H14: Klant | I14: 1 | J14: 50000 | K14: =IF($F14="Schuld",-1,IF($F14="",0,1)) | L14: Jaarrekening
B15: 46023 | C15: Overige schuld | D15: Consumptief krediet | E15: Persoonlijke lening | F15: Schuld | G15: Box 3 | H15: Gezamenlijk | I15: 0.5 | J15: 10000 | K15: =IF($F15="Schuld",-1,IF($F15="",0,1)) | L15: Handmatig
K16: =IF($F16="Schuld",-1,IF($F16="",0,1))
K17: =IF($F17="Schuld",-1,IF($F17="",0,1))
K18: =IF($F18="Schuld",-1,IF($F18="",0,1))
K19: =IF($F19="Schuld",-1,IF($F19="",0,1))
K20: =IF($F20="Schuld",-1,IF($F20="",0,1))
K21: =IF($F21="Schuld",-1,IF($F21="",0,1))
K22: =IF($F22="Schuld",-1,IF($F22="",0,1))
K23: =IF($F23="Schuld",-1,IF($F23="",0,1))
K24: =IF($F24="Schuld",-1,IF($F24="",0,1))
K25: =IF($F25="Schuld",-1,IF($F25="",0,1))
K26: =IF($F26="Schuld",-1,IF($F26="",0,1))
K27: =IF($F27="Schuld",-1,IF($F27="",0,1))
... K405: =IF($F405="Schuld",-1,IF($F405="",0,1))

Sheet 05_Historie
B2: MEERJARIGE SNAPSHOTS (trend)
B3: 05_Historie · Historische totalen per peildatum · actueel jaar volgt automatisch uit de berekeningen
B5: Peildatum | C5: Bezittingen | D5: Schulden | E5: Netto vermogen | F5: Bron
B6: 45292 | C6: 980000 | D6: 360000 | E6: =C6-D6 | F6: Vorig dossier
B7: 45658 | C7: 1060000 | D7: 345000 | E7: =C7-D7 | F7: Vorig dossier
B8: =Peildatum_Actueel | C8: ='11_Berekeningen'!$C$6 | D8: ='11_Berekeningen'!$C$7 | E8: =C8-D8 | F8: Actueel (berekend)

Sheet 11_Berekeningen
B2: BEREKENINGEN — KPI's, ratio's & consolidatie
B3: 11_Berekeningen · Alles gevoed door 04_Input_Vermogen · gefilterd op Peildatum_Actueel · geen hardcoded cijfers
B5: KPI / berekening | C5: Totaal | D5: Klant | E5: Partner | F5: Toelichting
B6: Totaal bezittingen | C6: =SUMIFS(v_Waarde,v_Type,"Bezitting",v_Peildatum,Peildatum_Actueel) | D6: =SUMPRODUCT((v_Peildatum=Peildatum_Actueel)*(v_Type="Bezitting")*v_Waarde*v_Aandeel) | E6: =SUMPRODUCT((v_Peildatum=Peildatum_Actueel)*(v_Type="Bezitting")*v_Waarde*(1-v_Aandeel)) | F6: alle bezittingen op peildatum
B7: Totaal schulden | C7: =SUMIFS(v_Waarde,v_Type,"Schuld",v_Peildatum,Peildatum_Actueel) | D7: =SUMPRODUCT((v_Peildatum=Peildatum_Actueel)*(v_Type="Schuld")*v_Waarde*v_Aandeel) | E7: =SUMPRODUCT((v_Peildatum=Peildatum_Actueel)*(v_Type="Schuld")*v_Waarde*(1-v_Aandeel)) | F7: alle schulden op peildatum
B8: NETTO VERMOGEN | C8: =C6-C7 | D8: =D6-D7 | E8: =E6-E7 | F8: bezittingen -/- schulden
B11: VERMOGEN PER CATEGORIE (bezittingen)
B12: Categorie | C12: Bedrag | D12: % van bezittingen
B13: Liquiditeiten | C13: =SUMIFS(v_Waarde,v_Categorie,B13,v_Peildatum,Peildatum_Actueel,v_Type,"Bezitting") | D13: =IFERROR(C13/$C$6,0)
B14: Vastgoed | C14: =SUMIFS(v_Waarde,v_Categorie,B14,v_Peildatum,Peildatum_Actueel,v_Type,"Bezitting") | D14: =IFERROR(C14/$C$6,0)
B15: Beleggingen | C15: =SUMIFS(v_Waarde,v_Categorie,B15,v_Peildatum,Peildatum_Actueel,v_Type,"Bezitting") | D15: =IFERROR(C15/$C$6,0)
B16: Pensioen/ODV | C16: =SUMIFS(v_Waarde,v_Categorie,B16,v_Peildatum,Peildatum_Actueel,v_Type,"Bezitting") | D16: =IFERROR(C16/$C$6,0)
B17: Onderneming/AB | C17: =SUMIFS(v_Waarde,v_Categorie,B17,v_Peildatum,Peildatum_Actueel,v_Type,"Bezitting") | D17: =IFERROR(C17/$C$6,0)
B18: Overige bezitting | C18: =SUMIFS(v_Waarde,v_Categorie,B18,v_Peildatum,Peildatum_Actueel,v_Type,"Bezitting") | D18: =IFERROR(C18/$C$6,0)
B20: RATIO'S & SIGNAALWAARDEN
B21: Ratio | C21: Waarde | D21: Norm/signaal
B22: Schuldratio (schulden / bezittingen) | C22: =IFERROR(C7/C6,0) | D22: =IF(IFERROR(C7/C6,0)>0.6,"⚠ hoog","OK")
B23: Verhouding zakelijk / totaal bezittingen | C23: =IFERROR((=SUMIFS(v_Waarde,v_Categorie,"Onderneming/AB",v_Peildatum,Peildatum_Actueel,v_Type,"Bezitting"))/C6,0) | D23: ="informatief"
B24: Liquiditeit (liquide middelen) | C24: =SUMIFS(v_Waarde,v_Categorie,"Liquiditeiten",v_Peildatum,Peildatum_Actueel,v_Type,"Bezitting") | D24: =IF((=SUMIFS(v_Waarde,v_Categorie,"Liquiditeiten",v_Peildatum,Peildatum_Actueel,v_Type,"Bezitting"))<20000,"⚠ laag","OK")
B25: Box 3-grondslag indicatief (monitor) | C25: =SUMIFS(v_Waarde,v_Box,"Box 3",v_Peildatum,Peildatum_Actueel,v_Type,"Bezitting")+SUMIFS(v_Waarde,v_Box,"Box 3",v_Peildatum,Peildatum_Actueel,v_Type,"Schuld")*-1 | D25: ="vgl. met 02_Input_IB"

Sheet 20_Dashboard
B2: VERMOGENSMONITOR — DASHBOARD
B3: =" Klant: "&Klant_Naam&" · Peildatum: "&TEXT(Peildatum_Actueel,"dd-mm-yyyy")&" · Partner: "&Heeft_Partner
B5: NETTO VERMOGEN | E5: BEZITTINGEN | H5: SCHULDEN | K5: SCHULDRATIO
B6: =calc_Netto | E6: =calc_Bezit | H6: =calc_Schuld | K6: =IFERROR(calc_Schuld/calc_Bezit,0)
B9: NETTO — KLANT | E9: NETTO — PARTNER | H9: LIQUIDITEIT | K9: BOX 3-GRONDSLAG
B10: =calc_NettoKlant | E10: =IF(Heeft_Partner="JA",calc_NettoPartner,0) | H10: =SUMIFS(v_Waarde,v_Categorie,"Liquiditeiten",v_Peildatum,Peildatum_Actueel,v_Type,"Bezitting") | K10: =calc_Box3Monitor
I28: ⚠ SIGNALEN & AANDACHTSPUNTEN
I29: =IF(IFERROR(calc_Schuld/calc_Bezit,0)>0.6,"⚠ Schuldratio hoog (>60%)","✓ Schuldratio binnen norm")
B30: (hulpdata grafiek) | I30: =IF(SUMIFS(v_Waarde,v_Categorie,"Liquiditeiten",v_Peildatum,Peildatum_Actueel,v_Type,"Bezitting")<20000,"⚠ Beperkte liquiditeit (<€20.000)","✓ Voldoende liquiditeit")
B31: Klant | C31: =calc_NettoKlant | I31: =IF(ABS(calc_Box3Monitor-IB_Box3_Grondslag)>10000,"⚠ Verschil box 3: monitor vs. aangifte >€10k","✓ Box 3 sluit aan met aangifte")
B32: Partner | C32: =IF(Heeft_Partner="JA",calc_NettoPartner,0) | I32: =IF(Heeft_Partner="NEE","ℹ Alleenstaand: partnervelden onderdrukt","ℹ Partner meegenomen in consolidatie")

Sheet 21_Scenario
B2: FINANCIËLE PLANNING — scenario's
B3: 21_Scenario · Basis / Optimistisch / Conservatief · aanpasbare aannames (geel) · startpunt = actueel netto vermogen
B5: AANNAMES (pas de gele cellen aan)
B6: Parameter | C6: Basis | D6: Optimistisch | E6: Conservatief | F6: Eenheid
B7: Horizon (jaren) | C7: 10 | D7: 10 | E7: 10 | F7: jr
B8: Jaarlijkse besparing / bijstorten | C8: 20000 | D8: 30000 | E8: 10000 | F8: €
B9: Rendement beleggend vermogen | C9: 0.04 | D9: 0.06 | E9: 0.02 | F9: %
B10: Jaarlijkse extra aflossing schuld | C10: 15000 | D10: 20000 | E10: 10000 | F10: €
B11: Grote mutatie (bedrag, éénmalig) | C11: 0 | D11: 0 | E11: 0 | F11: €
B12: Grote mutatie in jaar | C12: 5 | D12: 5 | E12: 5 | F12: jr
B13: Startvermogen (actueel netto) | C13: =calc_Netto
B15: PROJECTIE NETTO VERMOGEN
B16: Scenario \ Jaar | C16: 0 | D16: 1 | E16: 2 | F16: 3 | G16: 4 | H16: 5 | I16: 6 | J16: 7 | K16: 8 | L16: 9 | M16: 10
B17: Basis | C17: =calc_Netto | D17: =C17*(1+$C$9)+$C$8+IF($C$12=1,$C$11,0) | E17: =D17*(1+$C$9)+$C$8+IF($C$12=2,$C$11,0) | F17: =E17*(1+$C$9)+$C$8+IF($C$12=3,$C$11,0) | G17: =F17*(1+$C$9)+$C$8+IF($C$12=4,$C$11,0) | H17: =G17*(1+$C$9)+$C$8+IF($C$12=5,$C$11,0) | I17: =H17*(1+$C$9)+$C$8+IF($C$12=6,$C$11,0) | J17: =I17*(1+$C$9)+$C$8+IF($C$12=7,$C$11,0) | K17: =J17*(1+$C$9)+$C$8+IF($C$12=8,$C$11,0) | L17: =K17*(1+$C$9)+$C$8+IF($C$12=9,$C$11,0) | M17: =L17*(1+$C$9)+$C$8+IF($C$12=10,$C$11,0)
B18: Optimistisch | C18: =calc_Netto | D18: =C18*(1+$D$9)+$D$8+IF($D$12=1,$D$11,0) | E18: =D18*(1+$D$9)+$D$8+IF($D$12=2,$D$11,0) | F18: =E18*(1+$D$9)+$D$8+IF($D$12=3,$D$11,0) | G18: =F18*(1+$D$9)+$D$8+IF($D$12=4,$D$11,0) | H18: =G18*(1+$D$9)+$D$8+IF($D$12=5,$D$11,0) | I18: =H18*(1+$D$9)+$D$8+IF($D$12=6,$D$11,0) | J18: =I18*(1+$D$9)+$D$8+IF($D$12=7,$D$11,0) | K18: =J18*(1+$D$9)+$D$8+IF($D$12=8,$D$11,0) | L18: =K18*(1+$D$9)+$D$8+IF($D$12=9,$D$11,0) | M18: =L18*(1+$D$9)+$D$8+IF($D$12=10,$D$11,0)
B19: Conservatief | C19: =calc_Netto | D19: =C19*(1+$E$9)+$E$8+IF($E$12=1,$E$11,0) | E19: =D19*(1+$E$9)+$E$8+IF($E$12=2,$E$11,0) | F19: =E19*(1+$E$9)+$E$8+IF($E$12=3,$E$11,0) | G19: =F19*(1+$E$9)+$E$8+IF($E$12=4,$E$11,0) | H19: =G19*(1+$E$9)+$E$8+IF($E$12=5,$E$11,0) | I19: =H19*(1+$E$9)+$E$8+IF($E$12=6,$E$11,0) | J19: =I19*(1+$E$9)+$E$8+IF($E$12=7,$E$11,0) | K19: =J19*(1+$E$9)+$E$8+IF($E$12=8,$E$11,0) | L19: =K19*(1+$E$9)+$E$8+IF($E$12=9,$E$11,0) | M19: =L19*(1+$E$9)+$E$8+IF($E$12=10,$E$11,0)
B21: EINDWAARDE (na horizon)
B22: Scenario | C22: Eindvermogen | D22: Verschil t.o.v. basis
B23: Basis | C23: =M17 | D23: =M17-M17
B24: Optimistisch | C24: =M18 | D24: =M18-M17
B25: Conservatief | C25: =M19 | D25: =M19-M17

Sheet 90_Config
B2: CONFIGURATIE — centrale keuzelijsten & parameters
B3: 90_Config · Wijzigt zelden · geldt voor ALLE klanten · 1x per jaar fiscale cijfers bijwerken
B6: Categorieen | C6: TypeLijst | D6: BoxLijst | E6: EigenaarLijst | F6: BronLijst | G6: JaNee | H6: Betrouwbaar
B7: Liquiditeiten | C7: Bezitting | D7: Box 1 | E7: Klant | F7: Aangifte IB | G7: JA | H7: Vastgesteld
B8: Vastgoed | C8: Schuld | D8: Box 2 | E8: Partner | F8: Jaarrekening | G8: NEE | H8: Schatting
B9: Beleggingen | D9: Box 3 | E9: Gezamenlijk | F9: Handmatig
B10: Pensioen/ODV | D10: n.v.t. | F10: Bank
B11: Onderneming/AB
B12: Overige bezitting
B13: Hypotheek
B14: Overige schuld
B18: FISCALE PARAMETERS (jaartabel)
B19: Parameter | C19: Waarde | D19: Eenheid | E19: Toelichting / bron
B20: Box 3 heffingsvrij vermogen (p.p.) | C20: 57000 | D20: € | E20: [AANNAME voorbeeld] jaarlijks bijwerken
B21: Rendementspercentage overig (box 3) | C21: 0.06 | D21: % | E21: [AANNAME voorbeeld] fictief rendement
B22: Inflatie (default scenario) | C22: 0.02 | D22: % | E22: aanname planning
B23: Default rendement beleggingen | C23: 0.04 | D23: % | E23: aanname planning
B24: AOW-leeftijd (indicatief) | C24: 67 | D24: jr | E24: [AANNAME] afhankelijk geboortejaar

Sheet 91_Mapping
B2: MAPPINGTABEL — bronlabels → standaardcategorie
B3: 91_Mapping · Vangt afwijkende indelingen per klant/bron op zonder het datamodel te wijzigen
B5: Bronlabel (zoals in bestand) | C5: Standaardcategorie | D5: Standaard subcat. | E5: Standaard box | F5: Opmerking
B6: Betaalrekening / Rc bank | C6: Liquiditeiten | D6: Betaalrekening | E6: Box 3
B7: Spaardeposito | C7: Liquiditeiten | D7: Spaarrekening | E7: Box 3
B8: WOZ-waarde / eigen woning | C8: Vastgoed | D8: Eigen woning | E8: Box 1
B9: Effectendepot / aandelen | C9: Beleggingen | D9: Effectenportefeuille | E9: Box 3
B10: Aandelen in Holding | C10: Onderneming/AB | D10: Aanmerkelijk belang | E10: Box 2 | F10: =eigen vermogen BV
B11: Hypothecaire lening | C11: Hypotheek | D11: Eigenwoningschuld | E11: Box 1
B12: Rekening-courant DGA | C12: Overige schuld | D12: R/C DGA | E12: Box 2 | F12: teken afhankelijk saldo
B14: Werkwijze: bij import (Power Query, fase 2) wordt elk bronlabel via INDEX/MATCH vertaald naar de standaardcategorie. Nieuw label = één regel toevoegen; het datamodel blijft ongewijzigd.

Sheet 99_Controles
B2: KWALITEITS- & CONTROLEMECHANISMEN
B3: 99_Controles · Volledigheid · aansluitingen IB↔Monitor↔JR · signaalwaarden · status naar START
B5: Controle | C5: Status | D5: Toelichting
B6: Volledigheid: klantnaam + peildatum aanwezig | C6: =IF(AND(Klant_Naam<>"",Peildatum_Actueel<>""),"OK","ONVOLLEDIG") | D6: kernvelden op START
B7: Aansluiting box 3: monitor vs. aangifte IB | C7: =IF(ABS(calc_Box3Monitor-IB_Box3_Grondslag)<=10000,"OK","CONTROLEER") | D7: verschil > €10.000 = signaal
B8: Balans jaarrekening in evenwicht (activa = passiva) | C8: =IF('03_Input_JR'!$C$12='03_Input_JR'!$C$19,"OK","CONTROLEER") | D8: balanstotaal activa = passiva
B9: AB-waarde monitor vs. eigen vermogen BV | C9: =IF(ABS(SUMIFS(v_Waarde,v_Categorie,"Onderneming/AB",v_Type,"Bezitting")-JR_EigenVermogen)<=5000,"OK","CONTROLEER") | D9: aandelenwaarde ≈ EV BV
B10: Aandeel klant % ingevuld waar Eigenaar=Gezamenlijk | C10: =IF(SUMPRODUCT((v_Eigenaar="Gezamenlijk")*(v_Aandeel=0)*(v_Waarde<>0))=0,"OK","CONTROLEER") | D10: gezamenlijk zonder splitsing = fout
B11: Geen negatieve waarden ingevoerd (teken via Type) | C11: =IF(SUMPRODUCT((v_Waarde<0)*1)=0,"OK","CONTROLEER") | D11: waarde positief; Type stuurt teken
B12: Netto vermogen niet negatief | C12: =IF(calc_Netto>=0,"OK","LET OP") | D12: signaal bij negatief eigen vermogen
